Workbook

Sheet Project_Info
A1: Project Name: | B1: Zaker AI Platform
A2: Client: | B2: zakerai.org
A3: Created By: | B3: QA Team (Atef, Mahmoud, Abdalhamid, Hamza, Kamel)
A4: Creation Date: | B4: 2026-07-13
A5: Reviewed by:
A6: Type of Testing: | B6: System / Functional / Regression
A7: Version: | B7: v1.0
A8: Total Requirements: | B8: 144
A9: Drive materials and show case | B9: https://drive.google.com/drive/folders/1a5FFjiuuONhmn_3RtTCtsmp3mwZWFaV2

Sheet Summary_Report
A1: Zaker AI - Test Execution Summary
A3: Metric | B3: Value | D3: Author | E3: Total | F3: Passed | G3: Failed | H3: Blocked | I3: Not Executed
A4: Total Requirements | B4: =COUNTA(Requirements!A2:A145) -> 144 | D4: M_Atef | E4: =COUNTIF(Test_Cases!M2:M368,"M_Atef") -> 47 | F4: =COUNTIFS(Test_Cases!M2:M368,"M_Atef",Test_Cases!L2:L368,"Passed") -> 29 | G4: =COUNTIFS(Test_Cases!M2:M368,"M_Atef",Test_Cases!L2:L368,"Failed") -> 8 | H4: =COUNTIFS(Test_Cases!M2:M368,"M_Atef",Test_Cases!L2:L368,"Blocked") -> 0 | I4: =COUNTIFS(Test_Cases!M2:M368,"M_Atef",Test_Cases!L2:L368,"Not_Executed") -> 10
A5: Total User Stories | B5: =COUNTA(User_Stories!A2:A145) -> 144 | D5: Mahmoud Abdalazem | E5: =COUNTIF(Test_Cases!M2:M368,"Mahmoud Abdalazem") -> 0 | F5: =COUNTIFS(Test_Cases!M2:M368,"Mahmoud Abdalazem",Test_Cases!L2:L368,"Passed") -> 0 | G5: =COUNTIFS(Test_Cases!M2:M368,"Mahmoud Abdalazem",Test_Cases!L2:L368,"Failed") -> 0 | H5: =COUNTIFS(Test_Cases!M2:M368,"Mahmoud Abdalazem",Test_Cases!L2:L368,"Blocked") -> 0 | I5: =COUNTIFS(Test_Cases!M2:M368,"Mahmoud Abdalazem",Test_Cases!L2:L368,"Not_Executed") -> 0
A6: Total Test Cases | B6: =COUNTA(Test_Cases!A2:A368) -> 367 | D6: Abdelhamid Anwer | E6: =COUNTIF(Test_Cases!M2:M368,"Abdelhamid Anwer") -> 86 | F6: =COUNTIFS(Test_Cases!M2:M368,"Abdelhamid Anwer",Test_Cases!L2:L368,"Passed") -> 75 | G6: =COUNTIFS(Test_Cases!M2:M368,"Abdelhamid Anwer",Test_Cases!L2:L368,"Failed") -> 10 | H6: =COUNTIFS(Test_Cases!M2:M368,"Abdelhamid Anwer",Test_Cases!L2:L368,"Blocked") -> 0 | I6: =COUNTIFS(Test_Cases!M2:M368,"Abdelhamid Anwer",Test_Cases!L2:L368,"Not_Executed") -> 0
A7: Passed | B7: =COUNTIF(Test_Cases!L2:L368,"Passed") -> 295 | D7: Hamza | E7: =COUNTIF(Test_Cases!M2:M368,"Hamza") -> 47 | F7: =COUNTIFS(Test_Cases!M2:M368,"Hamza",Test_Cases!L2:L368,"Passed") -> 30 | G7: =COUNTIFS(Test_Cases!M2:M368,"Hamza",Test_Cases!L2:L368,"Failed") -> 16 | H7: =COUNTIFS(Test_Cases!M2:M368,"Hamza",Test_Cases!L2:L368,"Blocked") -> 0 | I7: =COUNTIFS(Test_Cases!M2:M368,"Hamza",Test_Cases!L2:L368,"Not_Executed") -> 1
A8: Failed | B8: =COUNTIF(Test_Cases!L2:L368,"Failed") -> 60 | D8: M_Kamel | E8: =COUNTIF(Test_Cases!M2:M368,"M_Kamel") -> 77 | F8: =COUNTIFS(Test_Cases!M2:M368,"M_Kamel",Test_Cases!L2:L368,"Passed") -> 70 | G8: =COUNTIFS(Test_Cases!M2:M368,"M_Kamel",Test_Cases!L2:L368,"Failed") -> 7 | H8: =COUNTIFS(Test_Cases!M2:M368,"M_Kamel",Test_Cases!L2:L368,"Blocked") -> 0 | I8: =COUNTIFS(Test_Cases!M2:M368,"M_Kamel",Test_Cases!L2:L368,"Not_Executed") -> 0
A9: Blocked | B9: =COUNTIF(Test_Cases!L2:L368,"Blocked") -> 0
A10: Not Executed | B10: =COUNTIF(Test_Cases!L2:L368,"Not_Executed") -> 11
A11: Pass Rate | B11: =IFERROR(B5/B4,0) -> 1
A12: Fail Rate | B12: =IFERROR(B6/B4,0) -> 2.5486111
A13: Total Bugs | B13: =COUNTA(Bug_Report!A2:A55) -> 54
A14: Critical Bugs | B14: =COUNTIF(Bug_Report!F2:F55,"Critical") -> 13
A15: High Bugs | B15: =COUNTIF(Bug_Report!F2:F55,"High") -> 18
A16: Medium Bugs | B16: =COUNTIF(Bug_Report!F2:F55,"Medium") -> 12
A17: Low Bugs | B17: =COUNTIF(Bug_Report!F2:F55,"Low") -> 11
A18: Requirements Fully Covered | B18: =COUNTIF(Traceability!J2:J145,"Fully Covered") -> 2
A19: Requirements Partially Covered | B19: =COUNTIF(Traceability!J2:J145,"Partial") -> 5
A20: Requirements Not Covered | B20: =COUNTIF(Traceability!J2:J145,"Not Covered") -> 131
A21: Requirements With Failures | B21: =COUNTIF(Traceability!J2:J145,"Failing") -> 6
A22: Coverage % | B22: =IFERROR((B16+B19)/B2,0) -> 0

Sheet Requirements
A1: Req_ID | B1: Description | C1: Module | D1: Priority | E1: Status | F1: Version
A2: FR-AUTH-01 | B2: The system shall allow new users to register with: phone number (required), username (required), password (required), and either an invitation code or a payment code (required). Email, first name, and last name are optional at registration. | C2: Auth | D2: P1 | E2: Active | F2: v1.0
A3: FR-AUTH-02 | B3: The system shall validate phone number uniqueness and email format at registration, rejecting duplicates with a descriptive error. | C3: Auth | D3: P1 | E3: Active | F3: v1.0
A4: FR-AUTH-03 | B4: Users shall log in using username and password credentials. | C4: Auth | D4: P1 | E4: Active | F4: v1.0
A5: FR-AUTH-04 | B5: Password reset shall be performed by the tenant admin only; the admin generates a new temporary password for the target user. Self-service password reset is not in scope for v1. | C5: Auth | D5: P1 | E5: Active | F5: v1.0
A6: FR-AUTH-05 | B6: Session tokens shall expire after 10 minutes of inactivity; the user shall be prompted to re-authenticate. | C6: Auth | D6: P1 | E6: Active | F6: v1.0
A7: FR-AUTH-06 | B7: Invitation codes are single-use and issued by the tenant admin; each code encodes the recipient's designated role on redemption. | C7: Auth | D7: P1 | E7: Active | F7: v1.0
A8: FR-AUTH-07 | B8: A user may register using a valid payment code in place of an invitation code when the tenant supports the payment-based enrollment model. | C8: Auth | D8: P1 | E8: Active | F8: v1.0
A9: FR-AUTH-08 | B9: The tenant admin can invite and manage users within the limits of the institution's active plan and tier. | C9: Auth | D9: P1 | E9: Active | F9: v1.0
A10: FR-AUTH-09 | B10: Students may join a subscription-based tenant by registering with a payment code that covers the subscription fee; the code amount is credited to the tenant balance. | C10: Auth | D10: P1 | E10: Active | F10: v1.0
A11: FR-AUTH-10 | B11: Students may join a tenant using an invitation code issued by the admin when the tenant operates on an invitation-only enrollment model. | C11: Auth | D11: P1 | E11: Active | F11: v1.0
A12: FR-AUTH-11 | B12: During tenant creation, the institution must specify its student enrollment model: invitation-code only, payment/subscription-based, or both. This setting determines which registration paths are enabled for that tenant. | C12: Tenant Setup | D12: P1 | E12: Active | F12: v1.0
... A145: FR-MNT-03 | B145: The platform shall comply with applicable data protection regulations for the regions in which it operates (e.g., GDPR, Egyptian Personal Data Protection Law). | C145: Compliance | D145: P2 | E145: Active | F145: v1.0

Sheet User_Stories
A1: US_ID | B1: Req_ID | C1: Module | D1: Role | E1: UserStory | F1: AcceptanceCriteria | G1: Priority
A2: US-001 | B2: FR-AUTH-01 | C2: Auth | D2: user | E2: As a user, I want allow new users to register with: phone number (required), username (required), password (required), and either an invitation code or a payment code (required). Email, first name, and last name are optional at registration., so that the auth behaviour meets the requirement. | F2: Given the preconditions defined in FR-AUTH-01, when the action described in the requirement is performed, then the system behaves exactly as specified: The system shall allow new users to register with: phone number (required), username (required), password (required), and either an invitation code or a payment code (required). Email, first name, and last name are optional at registration. | G2: P1
A3: US-002 | B3: FR-AUTH-02 | C3: Auth | D3: user | E3: As a user, I want validate phone number uniqueness and email format at registration, rejecting duplicates with a descriptive error., so that the auth behaviour meets the requirement. | F3: Given the preconditions defined in FR-AUTH-02, when the action described in the requirement is performed, then the system behaves exactly as specified: The system shall validate phone number uniqueness and email format at registration, rejecting duplicates with a descriptive error. | G3: P1
A4: US-003 | B4: FR-AUTH-03 | C4: Auth | D4: user | E4: As a user, I want log in using username and password credentials., so that the auth behaviour meets the requirement. | F4: Given the preconditions defined in FR-AUTH-03, when the action described in the requirement is performed, then the system behaves exactly as specified: Users shall log in using username and password credentials. | G4: P1
A5: US-004 | B5: FR-AUTH-04 | C5: Auth | D5: Head/Admin | E5: As a Head/Admin, I want password reset shall be performed by the tenant admin only; the admin generates a new temporary password for the target user, so that the auth behaviour meets the requirement. | F5: Given the preconditions defined in FR-AUTH-04, when the action described in the requirement is performed, then the system behaves exactly as specified: Password reset shall be performed by the tenant admin only; the admin generates a new temporary password for the target user. Self-service password reset is not in scope for v1. | G5: P1
A6: US-005 | B6: FR-AUTH-05 | C6: Auth | D6: user | E6: As a user, I want session tokens shall expire after 10 minutes of inactivity; the user shall be prompted to re-authenticate., so that the auth behaviour meets the requirement. | F6: Given the preconditions defined in FR-AUTH-05, when the action described in the requirement is performed, then the system behaves exactly as specified: Session tokens shall expire after 10 minutes of inactivity; the user shall be prompted to re-authenticate. | G6: P1
A7: US-006 | B7: FR-AUTH-06 | C7: Auth | D7: Head/Admin | E7: As a Head/Admin, I want invitation codes are single-use and issued by the tenant admin; each code encodes the recipient's designated role on redemption., so that the auth behaviour meets the requirement. | F7: Given the preconditions defined in FR-AUTH-06, when the action described in the requirement is performed, then the system behaves exactly as specified: Invitation codes are single-use and issued by the tenant admin; each code encodes the recipient's designated role on redemption. | G7: P1
A8: US-007 | B8: FR-AUTH-07 | C8: Auth | D8: user | E8: As a user, I want a user may register using a valid payment code in place of an invitation code when the tenant supports the payment-based enrollment model., so that the auth behaviour meets the requirement. | F8: Given the preconditions defined in FR-AUTH-07, when the action described in the requirement is performed, then the system behaves exactly as specified: A user may register using a valid payment code in place of an invitation code when the tenant supports the payment-based enrollment model. | G8: P1
A9: US-008 | B9: FR-AUTH-08 | C9: Auth | D9: Head/Admin | E9: As a Head/Admin, I want can invite and manage users within the limits of the institution's active plan and tier., so that the auth behaviour meets the requirement. | F9: Given the preconditions defined in FR-AUTH-08, when the action described in the requirement is performed, then the system behaves exactly as specified: The tenant admin can invite and manage users within the limits of the institution's active plan and tier. | G9: P1
A10: US-009 | B10: FR-AUTH-09 | C10: Auth | D10: student | E10: As a student, I want join a subscription-based tenant by registering with a payment code that covers the subscription fee; the code amount is credited to the tenant balance., so that the auth behaviour meets the requirement. | F10: Given the preconditions defined in FR-AUTH-09, when the action described in the requirement is performed, then the system behaves exactly as specified: Students may join a subscription-based tenant by registering with a payment code that covers the subscription fee; the code amount is credited to the tenant balance. | G10: P1
A11: US-010 | B11: FR-AUTH-10 | C11: Auth | D11: student | E11: As a student, I want join a tenant using an invitation code issued by the admin when the tenant operates on an invitation-only enrollment model., so that the auth behaviour meets the requirement. | F11: Given the preconditions defined in FR-AUTH-10, when the action described in the requirement is performed, then the system behaves exactly as specified: Students may join a tenant using an invitation code issued by the admin when the tenant operates on an invitation-only enrollment model. | G11: P1
A12: US-011 | B12: FR-AUTH-11 | C12: Tenant Setup | D12: student | E12: As a student, I want the institution must specify its student enrollment model: invitation-code only, payment/subscription-based, or both, so that the tenant setup behaviour meets the requirement. | F12: Given the preconditions defined in FR-AUTH-11, when the action described in the requirement is performed, then the system behaves exactly as specified: During tenant creation, the institution must specify its student enrollment model: invitation-code only, payment/subscription-based, or both. This setting determines which registration paths are enabled for that tenant. | G12: P1
... A145: US-144 | B145: FR-MNT-03 | C145: Compliance | D145: user | E145: As a user, I want the platform shall comply with applicable data protection regulations for the regions in which it operates (e.g., GDPR, Egyptian Personal Data Protection Law)., so that the compliance behaviour meets the requirement. | F145: Given the preconditions defined in FR-MNT-03, when the action described in the requirement is performed, then the system behaves exactly as specified: The platform shall comply with applicable data protection regulations for the regions in which it operates (e.g., GDPR, Egyptian Personal Data Protection Law). | G145: P2

Sheet Test_Cases
A1: TC_ID | B1: Scenario | C1: Req_ID | D1: Title | E1: Description | F1: Preconditions | G1: Test Steps | H1: Test Data | I1: Expected Result | J1: Postconditions | K1: Actual Result | L1: Status | M1: Author | N1: Execution Cycle | O1: Priority
A2: tc_001 | B2: Authontication | C2: FR-AUTH-01 | D2: Verification of Required and Optional Fields Presence on Registration Page | E2: To verify that the registration form displays all the specified fields upon loading, and to ensure that mandatory fields (Phone Number, Username, Password, Invitation/Payment Code) and optional fields (Email, First Name, Last Name) are correctly distinguished visually | F2: 1. The Tenant Portal platform is up and running. 2. The registration URL is publicly accessible without prior authentication | G2: 1. Open the web browser and navigate to the tenant's registration URL. 2. Verify the presence of all required fields and check if they are marked as mandatory 3. Verify the presence of optional fields and ensure they are not marked with mandatory indicators. | H2: N/A | I2: 1. The page loads successfully, displaying the ZAKER AI platform registration interface. 2. All req faild are visiable. | J2: The page remains loaded without submitting data or navigating away, with all input fields ready for user interactions. | K2: 1. The page loads successfully, displaying the ZAKER AI platform registration interface. 2. All req faild are visiable. | L2: Passed | M2: M_Atef | N2: v1.0 | O2: High
A3: tc_002 | B3: Authentication | C3: FR-AUTH-01 | D3: Successful Registration with Admin Invitation Code | E3: To verify that a user can successfully register by providing all mandatory fields and a valid invitation code from the admin | F3: 1. The platform is up and running. 2. A valid invitation code is provided by the admin. | G3: 1. Navigate to the registration page. 2. Enter a valid Phone Number, Username, and Password. 3. Enter the valid Admin Invitation Code. 4. Click the "Register" button. | H3: 1. Valid user details, Admin Code | I3: 1. The system validates the code. 2. The account is created successfully. 3. The user is redirected to the dashboard. | J3: User session is established and redirected to the main page. | K3: 1. The system validates the code. 2. The account is created successfully. 3. The user is redirected to the dashboard. | L3: Passed | M3: M_Atef | N3: v1.0 | O3: High
A4: tc_003 | B4: Authentication | C4: FR-AUTH-01 | D4: Verify Registration Fails When Phone Number Field is Left Blank | E4: To verify that the system blocks account creation and throws a validation error when a user fills out all required details but leaves the Phone Number field empty. | F4: 1. The Tenant Registration page is open and fully loaded. | G4: 1. Fill in all mandatory fields with valid data, but leave the Phone Number field completely blank 2. Click on the "Create Account" button. | H4: 1. Valid user details, Admin Code | I4: 1. Registration is blocked 2. An error massege should be appeare. | J4: No account is created, the user remains on the page, and a specific validation error is displayed. | K4: 1. Registration is blocked 2. An error massege should be appeare. | L4: Passed | M4: M_Atef | N4: v1.0 | O4: High
A5: tc_004 | B5: Authentication | C5: FR-AUTH-01 | D5: Verify Registration Fails When Username Field is Left Blank | E5: To verify that the system blocks account creation and throws a validation error when a user fills out all required details but leaves the Username field empty. | F5: 1. The Tenant Registration page is open and fully loaded. | G5: 1. Fill in all mandatory fields with valid data, but leave the Username field completely blank 2. Click on the "Create Account" button. | H5: 1. Valid user details, Admin Code | I5: 1. Registration is blocked 2. An error massege should be appeare. | J5: No account is created, the user remains on the page, and a specific validation error is displayed. | K5: 1. Registration is blocked 2. An error massege should be appeare. | L5: Passed | M5: M_Atef | N5: v1.0 | O5: High
A6: tc_005 | B6: Authentication | C6: FR-AUTH-01 | D6: Verify Registration Fails When Password Field is Left Blank | E6: To verify that the system blocks account creation and throws a validation error when a user fills out all required details but leaves the Password field empty. | F6: 1. The Tenant Registration page is open and fully loaded. | G6: 1. Fill in all mandatory fields with valid data, but leave the Password field completely blank 2. Click on the "Create Account" button. | H6: 1. Valid user details, Admin Code | I6: 1. Registration is blocked 2. An error massege should be appeare. | J6: No account is created, the user remains on the page, and a specific validation error is displayed. | K6: 1. Registration is blocked 2. An error massege should be appeare. | L6: Passed | M6: M_Atef | N6: v1.0 | O6: High
A7: tc_006 | B7: Authentication | C7: FR-AUTH-01 | D7: Verify Registration Fails When Invitation/Payment Code Field is Left Blank | E7: To verify that the system blocks account creation and throws a validation error when a user fills out all required details but leaves the Code field empty. | F7: 1. The Tenant Registration page is open and fully loaded. | G7: 1. Fill in all mandatory fields with valid data, but leave the Invitation/Payment Code field completely blank 2. Click on the "Create Account" button. | H7: 1. Valid user details, Admin Code | I7: 1. Registration is blocked 2. An error massege should be appeare. | J7: No account is created, the user remains on the page, and a specific validation error is displayed. | K7: 1. Registration is blocked 2. An error massege should be appeare. | L7: Passed | M7: M_Atef | N7: v1.0 | O7: High
A8: tc_007 | B8: Authentication | C8: FR-AUTH-01 | D8: Verify Successful Registration with Empty Optional Fields | E8: To verify that the system successfully creates a new user account when all mandatory fields are provided with valid data, but all optional fields (Email, First Name, Last Name) are left completely blank. | F8: 1. The Tenant Registration page is open and fully loaded. 2. A valid, unused Invitation or Payment Code is available. | G8: 1.Fill in all mandatory fields with valid data, but leave Email, First Name, and Last Name completely blank. 2. Click on the "Create Account" button. | H8: 1. Valid user details, Admin Code | I8: 1. The form submits successfully without any validation errors. 2. The user account is provisioned. 3. The user is redirected to the dashboard. | J8: The account is successfully created in the database, and the user is redirected to the platform dashboard with the appropriate role permissions. | K8: 1. The form submits successfully without any validation errors. 2. The user account is provisioned. 3. The user is redirected to the dashboard. | L8: Passed | M8: M_Atef | N8: v1.0 | O8: High
A9: tc_008 | B9: Authentication | C9: FR-AUTH-01 | D9: Authenticated User Access to Registration Page (Routing Bug) | E9: Verify that an already logged-in user is blocked from accessing the Registration page and is automatically redirected to the dashboard. | F9: 1. A valid user account is successfully logged into the platform. | G9: 1. While logged in, manually type the exact Registration URL in the browser's address bar and hit Enter. 2. Observe the system behavior and the loaded page. | H9: Registration Url: "https://mr-ali-magdy.zakerai.org/register" | I9: 1. Strictly blocks access to the registration form. 2. Automatically redirects the user back to their Home/Tenant Dashboard page smoothly. | J9: The user's active session remains intact, and no unauthenticated routes are rendered | K9: 1. The system allows access to the Registration page and renders the signup form despite the user having an active login session. | L9: Failed | M9: M_Atef | N9: v1.0 | O9: High
A10: tc_009 | B10: Authentication | C10: FR-AUTH-02 | D10: Verify Registration Fails with an Already Registered/Duplicate Phone Number | E10: To verify that the system prevents account creation and displays a descriptive error message when a user tries to register using a phone number that is already associated with an existing account within the same tenant. | F10: 1. A user account already exists in the system database with the phone number: 01277801995 2. The Tenant Registration page is open and fully loaded. | G10: 1.Fill in all mandatory fields with valid data, but use the already registered phone number. 2. Click on the "Create Account" button. | H10: 1. Valid user details, Admin Code 2. Phone : 01277801995 | I10: 1. The registration process is rejected. 2. A clear, descriptive error message is displayed | J10: No new account is created, the database remains unchanged, and the user is blocked on the registration screen with a validation error message. | K10: 1. The registration process is rejected. 2. A clear, descriptive error message is displayed | L10: Passed | M10: M_Atef | N10: v1.0 | O10: High
A11: tc_010 | B11: Authentication | C11: FR-AUTH-02 | D11: Verify Registration Fails with Invalid Email Formats | E11: To verify that the system blocks registration and displays a descriptive error message when the user provides an email address that does not follow the standard format (e.g., missing @, missing domain, or containing invalid characters). | F11: The Tenant Registration page is open and fully loaded. | G11: 1. Fill in all mandatory fields with valid data. 2. In the Email field, enter a format missing the @ symbol. | H11: 1. Valid user details, Admin Code 2. E_mail: mohamed_atefgmail.com | I11: 1. The system blocks submission and displays a descriptive error under the email field | J11: Registration is blocked, no user is created, and an inline validation error appears under the Email field. | K11: 1. The system blocks submission and displays a descriptive error under the email field | L11: Passed | M11: M_Atef | N11: v1.0 | O11: High
A12: tc_011 | B12: Authentication | C12: FR-AUTH-03 | D12: Successful Login (Happy Path) | E12: Verify that a user can successfully log in using a valid registered username and password. | F12: A valid user account exists with username 'mralimagdy_admin' and password '59wnqgF2e3Mo'. The login page is loaded. | G12: 1. Navigate to the login URL. 2. Enter a valid username. 3. Enter a valid password. 4. Click the 'Login' button. | H12: Username: 'mralimagdy_admin' Password: '59wnqgF2e3Mo' | I12: The system authenticates the user and redirects them to the home dashboard smoothly without errors. | J12: User is successfully authenticated, a valid JWT token is issued, and the user is redirected to the tenant dashboard. | K12: The system authenticates the user and redirects them to the home dashboard smoothly without errors. | L12: Passed | M12: M_Atef | N12: v1.0 | O12: High
... A18: tc_017 | B18: Authentication | C18: FR-AUTH-04 | D18: Verify Tenant Admin Can Successfully Generate a Temporary Password for a User | E18: o verify that the Tenant Admin has the functional capability to select a user account, trigger a password reset, and generate a valid temporary password successfully. | F18: 1. The Tenant Admin is logged into the Admin Dashboard 2. A target user account (e.g., student or teacher) exists within the tenant database. | G18: 1. Navigate to the "User Management" section in the Admin Dashboard. 2. Select the target user and click on the "Reset Password" button 3. Confirm the action to generate the temporary password | H18: N/A | I18: 1. The system successfully generates a secure temporary password. 2. A success notification is displayed. 3. The temporary credentials are delivered or shown to the admin. | J18: A temporary password is created, saved in the database, and the user's old password is instantly deactivated | K18: Feature isn'n available till now | L18: Not_Executed | M18: M_Atef | N18: v1.0 | O18: High
A19: tc_018 | B19: Authentication | C19: FR-AUTH-04 | D19: Verify User is Forced to Redirect to 'Change Password' Page on First Login with Temporary Credentials | E19: To verify that when a user logs in using a temporary password generated by the admin, the system automatically redirects them to a mandatory password change screen instead of the home dashboard. | F19: 1. The Tenant Admin has generated a temporary password for the user. 2. The user is on the standard login page | G19: 1. Enter the registered username and the freshly generated temporary password. 2. Click the 'Login' button. | H19: N/A | I19: 1. The system accepts the credentials. 2. Instead of loading the regular dashboard, the UI redirects the user directly to the mandatory /change-password page. 3. A clear prompt is displayed forcing the user to set a new password. | J19: The user session is restricted exclusively to the password update form until a new password is submitted. | L19: Not_Executed | M19: M_Atef | N19: v1.0 | O19: High
A20: tc_019 | B20: Authentication | C20: FR-AUTH-04 | D20: Verify Temporary Password Becomes Invalid After Being Changed | E20: To verify that the temporary password generated by the admin is permanently deactivated once the user uses it to log in and sets a new password. It must not be usable for any subsequent login attempts. | F20: 1. The Tenant Admin has reset the user's password and provided a temporary password. 2. The user has already logged in using that temporary password and successfully 3. updated it to a new custom password.The user is currently logged out. | G20: 1. Navigate to the tenant login page 2.Enter the registered username. 3. Enter the old temporary password provided previously by the admin. 4. Click the 'Login' button. | H20: N/A | I20: 1. The system rejects the login attempt. 2. An error message is displayed (e.g., "Invalid username or password"). | J20: Login is strictly blocked, no session token is generated, and the database rejects the old temporary credentials. | L20: Not_Executed | M20: M_Atef | N20: v1.0 | O20: High
A21: tc_020 | B21: Authentication | C21: FR-AUTH-04 | D21: Verify Successful Login Using the Newly Created Custom Password | E21: To verify that the system successfully authenticates the user when they attempt to log in using their newly updated permanent password after the reset flow. | F21: 1. The user has completed the password reset flow and updated their password to a permanent one. 2. The permanent password is saved in the system database. 3. The login page is loaded. | G21: 1. Navigate to the tenant login page 2.Enter the registered username. 3. Enter the newly created permanent password. 4. Click the 'Login' button. | H21: N/A | I21: 1. The system successfully authenticates the user, generates a JWT token, and redirects them to the home dashboard smoothly. | J21: User is successfully authenticated, a valid JWT token is issued, and the user is redirected to the home dashboard. | L21: Not_Executed | M21: M_Atef | N21: v1.0 | O21: High
A22: tc_021 | B22: Authentication | C22: FR-AUTH-05 | D22: Verify Session Token Expires After 10 Minutes of Total Inactivity | E22: To verify that the system automatically invalidates the session token and prompts the user to re-authenticate if no user activity is detected for a continuous duration of 10 minutes. | F22: 1. The user is successfully logged into the Tenant Dashboard with a valid, active session token | G22: 1. Log into the platform and navigate to any page inside the dashboard. 2. Leave the application completely idle (no mouse movement, no clicks, no keystrokes) for exactly 10 minutes 3. Observe the application interface immediately after the timer expires 4. Try to click on any button or refresh the page to execute a backend activity after expiry | H22: User: mralimagdy_admin pass: 59wnqgF2e3Mo 10 min of waiting | I22: 1. The session token expires server-side. 2. The UI prompts the user to re-authenticate | J22: The session token is completely invalidated, any subsequent API calls return unauthorized, and the user is redirected or prompted to re-log in. | K22: The session expired after 10 minutes of inactivity, and the user was successfully redirected to the login page for re-authentication. | L22: Not_Executed | M22: M_Atef | N22: v1.0 | O22: High
A23: tc_022 | B23: Authentication | C23: FR-AUTH-06 | D23: Verify New User is Assigned 'Teacher' Role Upon Using Teacher Invitation Code | E23: To verify that when a new user registers using an invitation code specifically generated for a Teacher, the system successfully provisions the account with strict Teacher permissions. | F23: 1. The Tenant Admin has generated an invitation code designated for the Teacher role. 2. The registration page is open. | G23: 1. Fill out all required registration fields and enter the Teacher invitation code. 2. Click "Register" and log into the newly created account. | H23: invite code: 68ed27c3-3bed-437d-9965-f48a72516f5b | I23: 1. Registration is successful. 2. The user is assigned the Teacher role. 3. The user can view class rosters but cannot access Admin billing or subscription settings. | J23: The account is created, and the user has access only to Teacher features (e.g., creating exams, viewing assigned classes). | K23: 1. Registration is successful. 2. The user is assigned the Teacher role. 3. The user can view class rosters but cannot access Admin billing or subscription settings. | L23: Passed | M23: M_Atef | N23: v1.0 | O23: High
A24: tc_023 | B24: Authentication | C24: FR-AUTH-06 | D24: Verify New User is Assigned 'Student' Role Upon Using Student Invitation Code | E24: To verify that when a new user registers using an invitation code specifically generated for a Student, the system successfully provisions the account with standard Student limits. | F24: 1. The Tenant Admin has generated an invitation code designated for the Student role. 2. The registration page is open. | G24: 1. Fill out all required registration fields and enter the Student invitation code. 2. Click "Register" and log into the newly created account. | H24: invite code: e270602e-42ea-4623-b0c1-027ba27eb5fe | I24: 1. Registration is successful. 2. The user is assigned the Student role. 3. The user can take assigned exams but cannot create exams or view other students' submissions. | J24: The account is created, and the user has access only to Student features (e.g., taking assigned exams, consuming courses). | K24: 1. Registration is successful. 2. The user is assigned the Student role. 3. The user can take assigned exams but cannot create exams or view other students' submissions. | L24: Passed | M24: M_Atef | N24: v1.0 | O24: High
A25: tc_024 | B25: Authentication | C25: FR-AUTH-06 | D25: Verify 'Admin' Role Assignment via Head Administrator Dashboard Actions | E25: To verify that an Admin account cannot self-register via codes, but is instead officially appointed and assigned tenant-wide permissions internally by the Head role. | F25: 1. The Tenant Admin has generated an invitation code designated for the Admin role. 2. The registration page is open. | G25: 1. Fill out all required registration fields and enter the Admin invitation code. 2. Click "Register" and log into the newly created account. | H25: invite code: b119f744-ecd2-4884-8576-40b0267c08f7 | I25: 1. Registration is successful. 2. The user is assigned the Admin role. 3. The user successfully accesses tenant-wide Admin features (can manage subscriptions, reset passwords, bulk import users) | J25: The target user account is upgraded to Tenant-wide Admin, gaining management access over resources, subscriptions, and billing | K25: 1. Registration is successful. 2. The user is assigned the Admin role. 3. The user successfully accesses tenant-wide Admin features (can manage subscriptions, reset passwords, bulk import users) | L25: Passed | M25: M_Atef | N25: v1.0 | O25: High
A26: tc_025 | B26: Authentication | C26: FR-AUTH-06 | D26: Verify System Blocks Invitation Code Generation for the 'Head' Role | E26: To verify that the system strictly prohibits the Tenant Admin (or any user) from generating an invitation code for the Head role, ensuring that there is always only one Head per organization as per the system design. | F26: 1. A Tenant Admin is logged into the Admin Dashboard. 2. The "Create Invitation Code" panel or endpoint is open. | G26: 1 .Navigate to the "Create Invitation Codes" section in the dashboard. 2. Open the Role Dropdown list to select the designated role for the new code 3. Select the 'Head' role and attempt to click the "Generate Code" button. | H26: 1. Selected Role: Head 2. cc945afc-5c01-46b5-b531-c5ae9b4f7504 | I26: 1. The 'Head' role must NOT be present in the dropdown list (Only Teacher, Student and Admin should be available). 2. [If selectable] The system blocks submission, rejects the request backend-side, and throws an error (e.g., "Cannot generate invitation code for Head role"). | J26: The system blocks the code generation, no database record is created for a Head invitation, and a restriction message is displayed. | K26: 1. The 'Head' role is visible and selectable in the dropdown list. 2. The system successfully generates an invitation code linked to the Head role. | L26: Failed | M26: M_Atef | N26: v1.0 | O26: High
A27: tc_026 | B27: Authentication | C27: FR-AUTH-08 | D27: Verify Registration Succeeds When Active User Count is Below Tier Limit | E27: To verify that the system successfully authenticates and creates a new user account when the current active user count is strictly less than the maximum tier capacity (e.g., 99 active users out of a 100-user limit) | F27: 1. The tenant is active on a plan tier restricted to a maximum of 100 active students/users. 2. The current active user count in the database is less than 100 . 3. The registration page is open. | G27: 1. Fill in all mandatory registration fields with valid data using an unused invitation or payment code. 2. Click on the "Register" / "Create Account" button. | H27: A valid data to regesteration with valid Invitation or payment . | I27: 1. The account is created successfully. 2. Total active user count incremented. | J27: The user account is successfully created and can browse courses and exams | K27: 1. The account is created successfully. 2. Total active user count incremented. | L27: Passed | M27: M_Atef | N27: v1.0 | O27: High
A28: tc_027 | B28: Authentication | C28: FR-AUTH-08 | D28: Verify Registration is Blocked When Active User Count Reaches Tier Limit | E28: To verify that the system strictly blocks any new account provisioning and authentication attempts if the tenant has already met its maximum plan capacity limit (e.g., attempting to register the 101st user when the limit is 100). | F28: 1. The tenant is active on a plan tier restricted to a maximum of 100 active users. 2. The current active user count in the database is exactly 100 (Full Capacity). 3. The registration page is open. | G28: 1. Fill in all mandatory registration fields with valid data using an unused invitation or payment code. 2. Click on the "Register" / "Create Account" button. | H28: A valid data to regesteration with valid Invitation or payment . | I28: 1. The runtime check detects that active users (100) have reached the plan limit (100). 2. Registration is blocked and no record is added to the database. 3. A descriptive error message is displayed (e.g., "Registration blocked: Institution capacity limit reached. Please contact your administrator." | J28: No account is created, the database user count stays at 100/100, and a descriptive plan limit warning/error is shown to the user. | K28: The registration was blocked when the active user limit was reached. No account was created, and an appropriate capacity limit message was displayed. | L28: Not_Executed | M28: M_Atef | N28: v1.0 | O28: High
A29: tc_028 | B29: Authentication | C29: FR-AUTH-10 | D29: Verify Student Can Successfully Register Using a Valid Invitation Code in an Invitation-Only Tenant | E29: To verify that when a specific tenant's setting is configured to work exclusively on an "invitation-only" enrollment model, the system successfully processes the student's registration upon providing a valid, unused invitation code. | F29: 1. A valid, unused student invitation code has been issued by the Tenant Admin 2. The student registration page for this specific tenant is loaded. | G29: 1. Fill out all mandatory registration fields (Phone, Username, Password). 2. In the "Code" field, enter the valid, unused Student Invitation Code. 3. Click on the "Create Account" button. | H29: invite code: e270602e-42ea-4623-b0c1-027ba27eb5fe | I29: 1. The system validates the code against the tenant's model configuration. 2. Registration completes successfully without billing intercepts. 3. The user is redirected to the main Student Dashboard | J29: The student account is successfully provisioned, the user is redirected to the student dashboard, and the code becomes invalid for future use. | K29: 1. The system validates the code against the tenant's model configuration. 2. Registration completes successfully without billing intercepts. 3. The user is redirected to the main Student Dashboard | L29: Passed | M29: M_Atef | N29: v1.0 | O29: High
A30: tc_029 | B30: Authentication | C30: Roles & Permmessions | D30: Verify Student Cannot Access Course Creation Interface or Controls | E30: To verify that when a user with the 'Student' role logs in, the system completely hides or disables all course creation elements (e.g., "Add Course" buttons, creation links) | F30: 1. A valid user account with the Student role exists. 2. The student is successfully logged into the platform. | G30: 1. Navigate to the main Courses tab 2. Visually inspect the top navigation bar, side menus, and page header for any "Add New Course", "Create Course", or "+" buttons. 3. Attempt to manually force access by typing the exact Admin/Teacher course creation URL into the browser's address bar. | H30: Url of create courses :https://mr-ali-magdy.zakerai.org/courses/create | I30: 1. There are no buttons or links related to creating or adding courses visible to the student. 2. The system intercepts the route, blocks access | J30: The student remains restricted to view-only mode, and no course creation interface is rendered | K30: 1. There are no buttons or links related to creating or adding courses visible to the student. 2. The system intercepts the route, blocks access | L30: Passed | M30: M_Atef | N30: v1.0 | O30: High
A31: tc_030 | B31: Authentication | C31: Roles & Permmessions | D31: Verify Tenant Admin Cannot Generate Invitation Codes for the 'Admin' Role | E31: To verify that the system strictly restricts the Tenant Admin from creating or generating an invitation code for the Admin role, enforcing that Admin privileges can only be granted internally by the Head account through role management. | F31: 1. A valid user account with the Admin role exists. 2. The Admin is successfully logged into the platform. | G31: 1. Navigate to the "Invitation Codes" section inside the Admin Dashboard 2. Open the designated Role Dropdown list to choose which role this invitation code will grant upon registration. | H31: N/A | I31: 1. The 'Admin' role must NOT be listed or available as an option in the dropdown (Only Teacher and Student should be selectable). | J31: The system blocks code generation for the Admin role, and the creation action is rejected both on the UI and backend levels. | K31: 1. Admin can create Admin's codes and Head's codes | L31: Failed | M31: M_Atef | N31: v1.0 | O31: High
A32: tc_031 | B32: Courses | C32: FR-CRS-01 | D32: Verify Head Can Successfully Create a New Course | E32: To verify that a user with the 'Head' role can fully create a course with a title, description, cover image, subject, price, and sections. | F32: 1. The Head user is successfully logged into the platform. | G32: 1. Click on the "Create Course" icon on the dashboard. 2. Enter valid course details and click Submit. | H32: A valid title, description, cover image, subject, price, and sections. | I32: 1. The course creation form opens successfully with fields: Title, Description, Cover Image, Subject, Price, and Sections. 2. The backend accepts the request, creates the database record, and a success message appears. | J32: A new Course was appear in Courses page | K32: 1. The form opens successfully. 2. Course is created successfully. | L32: Passed | M32: M_Atef | N32: v1.0 | O32: High
A33: tc_032 | B33: Authentication | C33: FR-CRS-01 | D33: Verify Tenant Admin Can Successfully Create a New Course | E33: To verify that a user with the 'Admin' role can fully create a course with a title, description, cover image, subject, price, and sections. | F33: 1. The Admin user is successfully logged into the platform. | G33: 1. Click on the "Create Course" icon on the dashboard. 2. Enter valid course details and click Submit. | H33: A valid title, description, cover image, subject, price, and sections. | I33: 1. The course creation form opens successfully with fields: Title, Description, Cover Image, Subject, Price, and Sections. 2. The backend accepts the request, creates the database record, and a success message appears. | J33: A new Course was appear in Courses page | K33: 1. The course creation form opens successfully with fields: Title, Description, Cover Image, Subject, Price, and Sections. 2. The backend accepts the request, creates the database record, and a success message appears. | L33: Passed | M33: M_Atef | N33: v1.0 | O33: High
... A158: TC_EXM_110 | B158: Exams | C158: FR-EXM-071 | D158: Verify Exams Dashboard Handles Slow Network Gracefully | E158: Verify that the Exams Dashboard behaves correctly under a slow network connection. | F158: Slow network simulation available. | G158: 1- Log in as Teacher/Admin.2- Simulate Slow 3G network.3- Open the Exams page.4- Perform search, filter and open an exam.5- Observe the application behavior. | H158: Slow 3G Network | I158: The system loads data correctly, displays loading indicators where applicable, and does not produce UI or functional errors. | J158: Dashboard remains stable under poor network conditions. | K158: The system functions as expected and all related configurations were verified successfully without any errors. | L158: Passed | M158: Mahmoud Abdalazem | N158: v1.0 | O158: High
A159: tc-01 | B159: Balance & Payment | C159: BAL-01 | D159: Admin Payment Added to Balance | E159: Verify that redeeming a valid payment code by the Head/Admin correctly increases the tenant balance. | F159: 1. A Head/Admin account exists. 2. The tenant balance is 0 EGP. 3. A valid unused payment code worth 100 EGP exists. | G159: 1. Log in as the Head/Admin. 2. Navigate to the Balance page. 3. Redeem the valid payment code. 4. Refresh the Balance page. | I159: 1. The payment code is redeemed successfully. 2. The tenant balance increases by 100 EGP. 3. The displayed balance is 100 EGP. 4. The redeemed payment code is marked as Redeemed. 5. The balance update is reflected immediately after refresh. | K159: 1. The payment code is redeemed successfully. 2. The tenant balance increases by 100 EGP. 3. The displayed balance is 100 EGP. 4. The redeemed payment code is marked as Redeemed. 5. The balance update is reflected immediately after refresh. | L159: Passed | M159: abdelhamid anwer | N159: v1.0
A160: tc-02 | B160: Balance & Payment | C160: BAL-01 | D160: Multiple Admin Payment Codes | E160: Verify that the tenant balance is updated correctly when the Head/Admin redeems multiple valid payment codes. | F160: 1. A Head/Admin account exists. 2. The tenant balance is 0 EGP. 3. Three valid unused payment codes exist with values of 100 EGP, 150 EGP, and 200 EGP. | G160: 1. Log in as the Head/Admin. 2. Navigate to the Balance page. 3. Redeem the first payment code. 4. Redeem the second payment code. 5. Redeem the third payment code. 6. Refresh the Balance page. | I160: 1. All three payment codes are redeemed successfully. 2. The tenant balance increases by 450 EGP. 3. The displayed balance is 450 EGP. 4. Each payment code is recorded successfully. | K160: 1. All three payment codes are redeemed successfully. 2. The tenant balance increases by 450 EGP. 3. The displayed balance is 450 EGP. 4. Each payment code is recorded successfully. | L160: Passed | M160: abdelhamid anwer | N160: v1.0
A161: tc-03 | B161: Balance & Payment | C161: BAL-01 | D161: Student Payment Added | E161: Verify that the tenant balance increases when a student joins using a valid payment code. | F161: 1. The tenant uses the payment-based enrollment model. 2. A valid unused payment code worth 150 EGP exists. 3. The student is not already registered. | G161: 1. Open the student registration page. 2. Enter valid student information. 3. Enter the valid payment code. 4. Complete the registration. 5. Log in as the Head/Admin. 6. Navigate to the Balance page. | I161: 1. The student account is created successfully. 2. The payment code is redeemed successfully. 3. The tenant balance increases by 150 EGP. 4. The updated balance is displayed correctly. | K161: 1. The student account is created successfully. 2. The payment code is redeemed successfully. 3. The tenant balance increases by 150 EGP. 4. The updated balance is displayed correctly. | L161: Passed | M161: abdelhamid anwer | N161: v1.0
A162: tc-04 | B162: Balance & Payment | C162: BAL-01 | D162: Combined Balance Calculation | E162: Verify that the tenant balance equals the sum of payment codes redeemed by both the Head/Admin and students. | F162: 1. The Head/Admin has redeemed payment codes totaling 300 EGP. 2. Two students have redeemed payment codes totaling 250 EGP. | G162: 1. Log in as the Head/Admin. 2. Navigate to the Balance page. | I162: 1. The displayed balance is 550 EGP. 2. The balance includes both Admin and student payment code values. 3. The balance calculation is accurate. | K162: 1. The displayed balance is 550 EGP. 2. The balance includes both Admin and student payment code values. 3. The balance calculation is accurate. | L162: Passed | M162: abdelhamid anwer | N162: v1.0
A163: tc-05 | B163: Balance & Payment | C163: BAL-01 | D163: Zero Initial Balance | E163: Verify that a newly created tenant has a balance of zero before any payment code is redeemed. | F163: 1. A new tenant has been created. 2. No payment codes have been redeemed. | G163: 1. Log in as the Head/Admin. 2. Navigate to the Balance page. | I163: 1. The displayed balance is 0 EGP. 2. No payment transactions are displayed. | K163: you can't intiate any platform without a balance | L163: Rejected | M163: abdelhamid anwer | N163: v1.0
A164: tc-06 | B164: Balance & Payment | C164: BAL-01 | D164: Failed Redemption Does Not Affect Balance | E164: Verify that an unsuccessful payment code redemption does not change the tenant balance. | F164: 1. The tenant balance is 300 EGP. 2. An invalid payment code is available. | G164: 1. Log in as the Head/Admin. 2. Navigate to the payment redemption page. 3. Enter the invalid payment code. 4. Submit the redemption request. 5. Navigate to the Balance page. | I164: 1. The redemption request is rejected. 2. An appropriate validation message is displayed. 3. The tenant balance remains 300 EGP. 4. No payment transaction is created. | K164: 1. The redemption request is rejected. 2. An appropriate validation message is displayed. 3. The tenant balance remains 300 EGP. 4. No payment transaction is created. | L164: Passed | M164: abdelhamid anwer | N164: v1.0
A165: tc-07 | B165: Balance & Payment | C165: BAL-01 | D165: Other Tenant Payments Excluded | E165: Verify that payment codes redeemed for another tenant are not included in the current tenant's balance. | F165: 1. Tenant A has redeemed payment codes totaling 200 EGP. 2. Tenant B has redeemed payment codes totaling 350 EGP. | G165: 1. Log in as the Head/Admin of Tenant A. 2. Navigate to the Balance page. 3. Record the displayed balance. 4. Log in as the Head/Admin of Tenant B. 5. Navigate to the Balance page. | I165: 1. Tenant A balance is 200 EGP. 2. Tenant B balance is 350 EGP. 3. Each tenant displays only its own balance. | K165: 1. Tenant A balance is 200 EGP. 2. Tenant B balance is 350 EGP. 3. Each tenant displays only its own balance. | L165: Passed | M165: abdelhamid anwer | N165: v1.0
A166: tc-08 | B166: Balance & Payment | C166: BAL-02 | D166: Successful Student Redemption | E166: Verify that a student can successfully redeem a valid payment code and that the payment value is credited to the tenant balance while both payment records are marked as Redeemed. | F166: 1. The tenant uses the payment-based enrollment model. 2. A valid unused payment code exists. 3. The student is not already registered. 4. The payment code belongs to the tenant. | G166: 1. Open the student registration page. 2. Enter valid student information. 3. Enter the valid payment code. 4. Submit the registration. 5. Log in as the Head/Admin. 6. Navigate to the Balance page. 7. Check the payment records. | I166: 1. The student account is created successfully. 2. The payment code is redeemed successfully. 3. The tenant balance increases by the payment code value. 4. The global payment record status is changed to Redeemed. 5. The tenant payment record status is changed to Redeemed. | K166: 1. The student account is created successfully. 2. The payment code is redeemed successfully. 3. The tenant balance increases by the payment code value. 4. The global payment record status is changed to Redeemed. 5. The tenant payment record status is changed to Redeemed. | L166: Passed | M166: abdelhamid anwer | N166: v1.0
A167: tc-10 | B167: Balance & Payment | C167: BAL-02 | D167: Redeemed Payment Code | E167: Verify that a payment code that has already been redeemed cannot be used again. | F167: 1. A payment code already exists with the status Redeemed. | G167: 1. Open the student registration page. 2. Enter valid student information. 3. Enter the redeemed payment code. 4. Submit the registration. | I167: 1. The registration is rejected. 2. An appropriate validation message is displayed. 3. The tenant balance remains unchanged. 4. The payment records remain unchanged. | K167: 1. The registration is rejected. 2. An appropriate validation message is displayed. 3. The tenant balance remains unchanged. 4. The payment records remain unchanged. | L167: Passed | M167: abdelhamid anwer | N167: v1.0
A168: tc-11 | B168: Balance & Payment | C168: BAL-02 | D168: Balance Updated | E168: Verify that the tenant balance is updated by the exact payment code value after a successful redemption. | F168: 1. The tenant balance is 500 EGP. 2. A valid unused payment code worth 150 EGP exists. | G168: 1. Register a student using the valid payment code. 2. Log in as the Head/Admin. 3. Navigate to the Balance page. | I168: 1. The tenant balance becomes 650 EGP. 2. The displayed balance is calculated correctly. | K168: 1. The tenant balance becomes 650 EGP. 2. The displayed balance is calculated correctly. | L168: Passed | M168: abdelhamid anwer | N168: v1.0
A169: tc-12 | B169: Balance & Payment | C169: BAL-03 | D169: Valid Payment Code | E169: Verify that the Head/Admin can successfully redeem a valid unused payment code and the balance is updated. | F169: 1. A Head/Admin account exists. 2. A valid unused payment code exists. 3. The tenant balance is 0 EGP. | G169: 1. Log in as the Head/Admin. 2. Navigate to the Payment Code page. 3. Enter the valid payment code. 4. Submit the payment code. 5. Navigate to the Balance page. | I169: 1. The payment code is accepted. 2. The payment code is marked as Redeemed. 3. The tenant balance increases by the payment code value. 4. A success message is displayed. | K169: 1. The payment code is accepted. 2. The payment code is marked as Redeemed. 3. The tenant balance increases by the payment code value. 4. A success message is displayed. | L169: Passed | M169: abdelhamid anwer | N169: v1.0
A170: tc-13 | B170: Balance & Payment | C170: BAL-03 | D170: Duplicate Payment Code | E170: Verify that duplicate payment codes are not accepted because payment codes must be globally unique. | F170: 1. A payment code already exists in the system. 2. The payment code has already been generated. | G170: 1. Log in as the Head/Admin. 2. Navigate to the Payment Code page. 3. Enter the duplicate payment code. 4. Submit the payment code. | I170: 1. The payment code is rejected. 2. An appropriate validation message is displayed. 3. The tenant balance remains unchanged. | K170: 1. The payment code is rejected. 2. An appropriate validation message is displayed. 3. The tenant balance remains unchanged. | L170: Passed | M170: abdelhamid anwer | N170: v1.0
... A243: tc-86 | B243: Balance & Payment | C243: SUB-14 | D243: Verify Exported CSV Format | E243: Verify that the exported file is generated in a valid CSV format with accurate data. | F243: 1. A Head/Admin account exists. 2. Exportable subscription data exists. | G243: 1. Export one of the available reports. 2. Open the exported CSV file using a spreadsheet application. 3. Review the file contents. | I243: 1. The exported file is in CSV format. 2. Column headers are displayed correctly. 3. Data is separated correctly into columns. 4. Exported values match the data displayed in the system. | K243: 1. The exported file is in CSV format. 2. Column headers are displayed correctly. 3. Data is separated correctly into columns. 4. Exported values match the data displayed in the system. | L243: Passed | M243: abdelhamid anwer | N243: v1.0
A244: tc-87 | B244: Balance & Payment | L244: Passed | M244: abdelhamid anwer | N244: v1.0
A245: EC-01 | B245: Exams | C245: FR-EXM | D245: Verify user can create a new exam with all valid required data | E245: Verify user can create a new exam with all valid required data | F245: User is logged in with permission to create exams; is on the 'Create Exam' page | G245: 1. Enter exam name 2. Set duration 3. Set start date/end date 4. Add one or more questions 5. Click 'Create' / 'Save' / 'Publish' | H245: Name: 'Midterm Exam 1' Duration: 60 minutes Start: today End: +7 days Questions: 10 selected | I245: Exam is created successfully; success message is shown; exam appears in the exams list with correct details | K245: pass | L245: Passed | M245: Hamza | N245: v1.0 | O245: High
A246: EC-02 | B246: Exams | C246: FR-EXM | D246: Verify system prevents exam creation when required fields are missing | E246: Verify system prevents exam creation when required fields are missing | F246: User is on the 'Create Exam' page | G246: 1. Leave a required field empty (e.g. exam name) 2. Attempt to click 'Create' / 'Save' | H246: Name: (empty) | I246: Validation error is shown for the missing field; exam is not created | K246: pass | L246: Passed | M246: Hamza | N246: v1.0 | O246: High
A247: EC-03 | B247: Exams | C247: FR-EXM | D247: Verify system rejects an exam with zero or negative duration | E247: Verify system rejects an exam with zero or negative duration | F247: User is on the 'Create Exam' page | G247: 1. Fill in all fields 2. Enter duration = 0 or a negative number 3. Attempt to save | H247: Duration: 0 / -10 | I247: Validation error is displayed; exam creation is blocked | K247: fail | L247: Failed | M247: Hamza | N247: v1.0 | O247: Medium
A248: EC-04 | B248: Exams | C248: FR-EXM | D248: Verify system rejects an exam where the end date/time is before the start date/time | E248: Verify system rejects an exam where the end date/time is before the start date/time | F248: User is on the 'Create Exam' page | G248: 1. Fill in all fields 2. Set End Date earlier than Start Date 3. Attempt to save | H248: Start: 2026-07-15, End: 2026-07-10 | I248: Validation error is displayed (e.g. 'End date must be after start date'); exam is not created | K248: pass | L248: Passed | M248: Hamza | N248: v1.0 | O248: High
A249: EC-05 | B249: Exams | C249: FR-EXM | D249: Verify user can add and remove questions while creating an exam | E249: Verify user can add and remove questions while creating an exam | F249: User is on the 'Create Exam' page with the question bank available | G249: 1. Add several questions to the exam 2. Remove one of the added questions 3. Save the exam | H249: Add 5 questions, remove 1 | I249: Only the remaining 4 questions are included in the saved exam | K249: fail | L249: Failed | M249: Hamza | N249: v1.0 | O249: Medium
A250: EC-06 | B250: Exams | C250: FR-EXM | D250: Verify system prevents creating an exam with zero questions | E250: Verify system prevents creating an exam with zero questions | F250: User is on the 'Create Exam' page | G250: 1. Fill in exam details 2. Do not add any questions 3. Attempt to save/publish | H250: Questions: none | I250: Validation error is shown; exam with no questions cannot be published | K250: pass | L250: Passed | M250: Hamza | N250: v1.0 | O250: Medium
A251: EC-07 | B251: Exams | C251: FR-EXM | D251: Verify duplicate exam name handling | E251: Verify duplicate exam name handling | F251: An exam with a specific name already exists | G251: 1. Create a new exam using the exact same name as an existing exam 2. Attempt to save | H251: Name: same as an existing exam | I251: System either warns about duplicate names or allows it per design; behavior should be consistent and documented (raise as a question if undefined) | K251: fail | L251: Failed | M251: Hamza | N251: v1.0 | O251: Low
A252: EC-08 | B252: Exams | C252: FR-EXM | D252: Verify exam can be saved as a draft without publishing | E252: Verify exam can be saved as a draft without publishing | F252: 'Save as Draft' option exists on the 'Create Exam' page | G252: 1. Fill in partial exam data 2. Click 'Save as Draft' (not Publish) | H252: Partial data | I252: Exam is saved with a 'Draft' status and is not visible/available to students until published | K252: pass | L252: Passed | M252: Hamza | N252: v1.0 | O252: Medium
A253: EC-09 | B253: Exams | C253: FR-EXM | D253: Verify max character limits on exam name/description fields are enforced | E253: Verify max character limits on exam name/description fields are enforced | F253: User is on the 'Create Exam' page | G253: 1. Enter an exam name exceeding the allowed character limit 2. Attempt to save | H253: Name: 300+ character string | I253: System either truncates input or shows a validation message; no crash or database error occurs | K253: pass | L253: Passed | M253: Hamza | N253: v1.0 | O253: Low
A254: EC-10 | B254: Exams | C254: FR-EXM | D254: Verify a created exam is correctly visible/assigned to the intended students/group | E254: Verify a created exam is correctly visible/assigned to the intended students/group | F254: Exam creation supports assigning to specific students or groups | G254: 1. Create an exam and assign it to a specific student group 2. Log in as a student in that group and check exam visibility 3. Log in as a student NOT in that group and check visibility | H254: Group A vs Group B | I254: Only students in the assigned group can see/access the exam | K254: pass | L254: Passed | M254: Hamza | N254: v1.0 | O254: High
A255: EC-11 | B255: Exams | C255: FR-EXM | D255: Verify creating an exam with randomized question order per student attempt | E255: Verify creating an exam with randomized question order per student attempt | F255: 'Randomize question order' option is available on the Create Exam page | G255: 1. Enable 'Randomize question order' 2. Save and publish the exam 3. Have two different students start the exam | H255: Randomize: ON | I255: Each student sees questions in a different order while all questions/content remain identical | K255: pass | L255: Passed | M255: Hamza | N255: v1.0 | O255: Medium
A256: EC-12 | B256: Exams | C256: FR-EXM | D256: Verify creating an exam with randomized answer choices order for MCQ questions | E256: Verify creating an exam with randomized answer choices order for MCQ questions | F256: Exam contains MCQ questions with a 'shuffle answers' option | G256: 1. Enable 'Shuffle answer choices' 2. Save and publish 3. Compare choice order for two different students | H256: Shuffle answers: ON | I256: Answer choice order differs between students while the correct-answer mapping remains accurate | K256: fail | L256: Failed | M256: Hamza | N256: v1.0 | O256: Medium
... A291: ES-23 | B291: Exams | C291: FR-EXM | D291: Verify the teacher can export exam results in bulk (e.g. CSV/Excel) | E291: Verify the teacher can export exam results in bulk (e.g. CSV/Excel) | F291: Exam has multiple student submissions; export feature is available | G291: 1. Open the exam's results/grades page 2. Click 'Export' and choose a format (e.g. CSV/Excel) 3. Open the exported file | H291: Export format: CSV | I291: An accurate file is downloaded containing all student names, scores, and submission statuses matching what's shown on screen | K291: fail | L291: Failed | M291: Hamza | N291: v1.0 | O291: Medium
A292: LPS-01 | B292: Landing Page Sections - Admin | D292: Open the tab | E292: Open the tab | G292: Go to Profile > 'اجزاء الصفحة الرأيسية' (Landing Page Sections) tab | I292: The page opens and shows the section list with a count badge | L292: Passed | M292: M_Kamel | N292: v1.0
A293: LPS-02 | B293: Landing Page Sections - Admin | D293: Empty state message | E293: Empty state message | G293: Open the tab when no sections exist yet | I293: Page shows 'لا توجد أقسام بعد' message with a 'Create Section' button | L293: Passed | M293: M_Kamel | N293: v1.0
A294: LPS-03 | B294: Landing Page Sections - Admin | D294: Open create form | E294: Open create form | G294: Click the 'قسم جديد' (New Section) button | I294: A popup (modal) opens titled 'قسم جديد' with empty fields | L294: Passed | M294: M_Kamel | N294: v1.0
A295: LPS-04 | B295: Landing Page Sections - Admin | D295: Close form with X | E295: Close form with X | G295: Open the create form, then click the X icon top right | I295: Form closes and no section is created | L295: Passed | M295: M_Kamel | N295: v1.0
A296: LPS-05 | B296: Landing Page Sections - Admin | D296: Close form with Cancel | E296: Close form with Cancel | G296: Open the create form, fill some fields, then click 'Cancel' | I296: Form closes and nothing is saved | L296: Passed | M296: M_Kamel | N296: v1.0
A297: LPS-06 | B297: Landing Page Sections - Admin | D297: Required field - Title | E297: Required field - Title | G297: Leave 'العنوان' (Title) empty and try to submit | I297: Form shows an error and does not save | L297: Passed | M297: M_Kamel | N297: v1.0
A298: LPS-07 | B298: Landing Page Sections - Admin | D298: Required field - Subtitle | E298: Required field - Subtitle | G298: Leave 'العنوان الفرعي' (Subtitle) empty and try to submit | I298: Form shows an error and does not save | L298: Passed | M298: M_Kamel | N298: v1.0
A299: LPS-08 | B299: Landing Page Sections - Admin | D299: Required field - Order | E299: Required field - Order | G299: Leave 'ترتيب العرض' (Display Order) empty and try to submit | I299: Form shows an error and does not save | K299: it cant be deleted its 1 by default | L299: Failed | M299: M_Kamel | N299: v1.0
A300: LPS-09 | B300: Landing Page Sections - Admin | D300: Order minimum value | E300: Order minimum value | G300: Enter 0 or a negative number in Display Order | I300: Form should reject it (minimum allowed is 1) | L300: Passed | M300: M_Kamel | N300: v1.0
A301: LPS-10 | B301: Landing Page Sections - Admin | D301: Create a valid section | E301: Create a valid section | G301: Fill Title, Subtitle, Order and 1 card with 1 point, then click 'إنشاء القسم' | I301: Section is created and appears in the list, count badge goes up by 1 | L301: Passed | M301: M_Kamel | N301: v1.0
A302: LPS-11 | B302: Landing Page Sections - Admin | D302: Add extra card | E302: Add extra card | G302: In the form, click 'إضافة بطاقة' (Add Card) | I302: A new empty card box is added below the existing one | K302: it gives error when card is empty | L302: Failed | M302: M_Kamel | N302: v1.0
A303: LPS-12 | B303: Landing Page Sections - Admin | D303: Remove a card | E303: Remove a card | G303: With 2+ cards, click the X on one card | I303: That card is removed from the form | L303: Passed | M303: M_Kamel | N303: v1.0
A304: LPS-13 | B304: Landing Page Sections - Admin | D304: Card order buttons disabled with 1 card | E304: Card order buttons disabled with 1 card | G304: With only 1 card in the form, check the up/down arrows on it | I304: Both up and down arrows are disabled (greyed out) | K304: it can be prdered high even if only one | L304: Failed | M304: M_Kamel | N304: v1.0
A305: LPS-14 | B305: Landing Page Sections - Admin | D305: Card order buttons enabled with 2+ cards | E305: Card order buttons enabled with 2+ cards | G305: Add a second card, check the up/down arrows | I305: Arrows become active and clickable | L305: Passed | M305: M_Kamel | N305: v1.0
A306: LPS-15 | B306: Landing Page Sections - Admin | D306: Reorder cards | E306: Reorder cards | G306: With 2+ cards, click the up arrow on the second card | I306: Second card moves above the first card | L306: Passed | M306: M_Kamel | N306: v1.0
A307: LPS-16 | B307: Landing Page Sections - Admin | D307: Card title field | E307: Card title field | G307: Type a card title in 'عنوان البطاقة' | I307: Text is entered and saved with the card | L307: Passed | M307: M_Kamel | N307: v1.0
A308: LPS-17 | B308: Landing Page Sections - Admin | D308: Pick card icon | E308: Pick card icon | G308: Click the icon button next to a card title | I308: An icon picker opens and lets you choose an icon | L308: Passed | M308: M_Kamel | N308: v1.0
A309: LPS-18 | B309: Landing Page Sections - Admin | D309: Add point to card | E309: Add point to card | G309: Click 'إضافة نقطة' (Add Point) inside a card | I309: A new numbered point field is added (e.g. '2.') | L309: Passed | M309: M_Kamel | N309: v1.0
A310: LPS-19 | B310: Landing Page Sections - Admin | D310: Remove point disabled with 1 point | E310: Remove point disabled with 1 point | G310: With only 1 point in a card, check its X button | I310: X button is disabled, point cannot be removed | L310: Passed | M310: M_Kamel | N310: v1.0
A311: LPS-20 | B311: Landing Page Sections - Admin | D311: Remove point enabled with 2+ points | E311: Remove point enabled with 2+ points | G311: Add a 2nd point, then check X buttons | I311: X buttons become active | L311: Passed | M311: M_Kamel | N311: v1.0
A312: LPS-21 | B312: Landing Page Sections - Admin | D312: Remove a point and renumber | E312: Remove a point and renumber | G312: With 3 points, remove the 2nd one | I312: Remaining points are renumbered correctly (1, 2) | L312: Passed | M312: M_Kamel | N312: v1.0
A313: LPS-22 | B313: Landing Page Sections - Admin | D313: Long text handling | E313: Long text handling | G313: Enter a very long Title (100+ characters) | I313: Text is accepted and layout does not break/overlap | L313: Passed | M313: M_Kamel | N313: v1.0
A314: LPS-23 | B314: Landing Page Sections - Admin | D314: Arabic + numbers + symbols | E314: Arabic + numbers + symbols | G314: Enter Arabic text mixed with numbers/symbols in Title/Subtitle | I314: Text saves correctly and displays in right-to-left (RTL) order | L314: Passed | M314: M_Kamel | N314: v1.0
A315: LPS-24 | B315: Landing Page Sections - Admin | D315: Edit existing section | E315: Edit existing section | G315: Click on an existing section in the list to edit it | I315: Edit form opens pre-filled with that section's current data | L315: Passed | M315: M_Kamel | N315: v1.0
A316: LPS-25 | B316: Landing Page Sections - Admin | D316: Update a section | E316: Update a section | G316: Change the title of an existing section and save | I316: List updates to show the new title | L316: Passed | M316: M_Kamel | N316: v1.0
... A319: LPS-28 | B319: Landing Page Sections - Admin | D319: Cancel delete | E319: Cancel delete | G319: Click delete then cancel the confirmation | I319: Section is NOT removed, still shown in the list | L319: Passed | M319: M_Kamel | N319: v1.0
A320: LPF-01 | B320: Landing Page Sections - On Website | D320: Sections appear on home page | E320: Sections appear on home page | G320: Create a section in admin, then open the public home page | I320: New section is visible on the home page | K320: only after old cach is deleted 5 mins | L320: Passed | M320: M_Kamel | N320: v1.0
A321: LPF-02 | B321: Landing Page Sections - On Website | D321: Sections follow display order | E321: Sections follow display order | G321: Create 2+ sections with different Order numbers, open home page | I321: Sections appear on the page in the same order as the numbers set | L321: Passed | M321: M_Kamel | N321: v1.0
A322: LPF-03 | B322: Landing Page Sections - On Website | D322: Title & subtitle shown correctly | E322: Title & subtitle shown correctly | G322: Compare the Title/Subtitle entered in admin with what shows on home page | I322: Text matches exactly, no missing or cut text | L322: Passed | M322: M_Kamel | N322: v1.0
A323: LPF-04 | B323: Landing Page Sections - On Website | D323: All cards shown | E323: All cards shown | G323: Create a section with 3 cards, check home page | I323: All 3 cards are visible on the home page | L323: Passed | M323: M_Kamel | N323: v1.0
A324: LPF-05 | B324: Landing Page Sections - On Website | D324: Card icons shown correctly | E324: Card icons shown correctly | G324: Pick a specific icon for a card in admin, check home page | I324: Same icon appears next to the card on the home page | L324: Passed | M324: M_Kamel | N324: v1.0
A325: LPF-06 | B325: Landing Page Sections - On Website | D325: Points/bullets shown | E325: Points/bullets shown | G325: Add 3 points to a card, check home page | I325: All 3 points are visible under that card | L325: Passed | M325: M_Kamel | N325: v1.0
A326: LPF-07 | B326: Landing Page Sections - On Website | D326: Mobile view | E326: Mobile view | G326: Open home page on a mobile size screen (or resize browser) | I326: Section still looks correct and readable, no overlap | L326: Passed | M326: M_Kamel | N326: v1.0
A327: LPF-08 | B327: Landing Page Sections - On Website | D327: RTL layout on site | E327: RTL layout on site | G327: Check text alignment/direction of the section on home page | I327: Everything reads right-to-left correctly (Arabic layout) | L327: Passed | M327: M_Kamel | N327: v1.0
A328: LPF-09 | B328: Landing Page Sections - On Website | D328: Delete reflects on site | E328: Delete reflects on site | G328: Delete a section from admin, refresh the home page | I328: Deleted section no longer appears on the home page | L328: Passed | M328: M_Kamel | N328: v1.0
A329: LPF-10 | B329: Landing Page Sections - On Website | D329: Edit reflects on site | E329: Edit reflects on site | G329: Edit a section's text in admin, refresh the home page | I329: Home page shows the updated text, not the old one | L329: Passed | M329: M_Kamel | N329: v1.0
A330: SUB-01 | B330: Subscription - Usage Numbers | D330: View plan details | E330: View plan details | G330: Open Subscription tab | I330: Plan name, billing cycle, start date, end date, max students, and price all display correctly | L330: Passed | M330: M_Kamel | N330: v1.0
A331: SUB-02 | B331: Subscription - Usage Numbers | D331: Check real user count | E331: Check real user count | G331: Open Users tab and count how many users actually exist (e.g. 9 users) | I331: Note down the real number of users | L331: Passed | M331: M_Kamel | N331: v1.0
A332: SUB-03 | B332: Subscription - Usage Numbers | D332: Compare usage number (BUG CHECK) | E332: Compare usage number (BUG CHECK) | G332: Go back to Subscription tab, check 'المستخدمون الحاليون' (Current Users) number | I332: Should match the real number of users counted in Users tab (currently shows 0, which is wrong) | L332: Passed | M332: M_Kamel | N332: v1.0
... A344: REN-08 | B344: Subscription - Renew Button | D344: Renew button state after expiry with no action | E344: Renew button state after expiry with no action | G344: Let subscription expire and do not renew, refresh page | I344: Page should still clearly indicate expired status until user renews | L344: Failed | M344: M_Kamel | N344: v1.0
A345: CQ-01 | B345: Classification - Level dropdown | D345: Verify Level dropdown loads options on page load | E345: Verify Level dropdown loads options on page load | G345: 1. Open the Create Question page 2. Observe the Level dropdown | H345: N/A | I345: Level dropdown shows 'Loading…' initially, then populates with a list of levels (Stage — Grade) from the API | L345: Passed | M345: M_Kamel | N345: v1.0
A346: CQ-02 | B346: Classification - Subject dropdown | D346: Verify Subject dropdown is disabled until a Level is selected | E346: Verify Subject dropdown is disabled until a Level is selected | G346: 1. Load the page without selecting a Level 2. Check Subject dropdown state | H346: N/A | I346: Subject dropdown is disabled and shows 'Select level first' | L346: Passed | M346: M_Kamel | N346: v1.0
A347: CQ-03 | B347: Classification - Cascading dropdowns | D347: Verify selecting a Level loads correct Subjects, and selecting Subject loads Chapters, and Chapter loads Lessons | E347: Verify selecting a Level loads correct Subjects, and selecting Subject loads Chapters, and Chapter loads Lessons | G347: 1. Select a Level 2. Wait for Subject list to load and select a Subject 3. Select a Chapter 4. Select a Lesson | H347: Any valid Level e.g. 'Primary — Grade 3' | I347: Each dependent dropdown becomes enabled and populated only after its parent is selected; changing a parent resets and disables all its children | L347: Passed | M347: M_Kamel | N347: v1.0
A348: CQ-04 | B348: Classification - Metadata fields | D348: Verify Difficulty, Time and Points fields have correct default values | E348: Verify Difficulty, Time and Points fields have correct default values | G348: 1. Load the page and inspect the Difficulty, Time (min), and Points fields | H348: N/A | I348: Difficulty defaults to 'Medium', Time (min) defaults to 5, Points defaults to 1 | L348: Passed | M348: M_Kamel | N348: v1.0
...

Sheet Bug_Report
A1: Bug_ID | B1: Module / Feature | C1: Title / Summary | D1: Reported By | E1: Detected In / Test Cycle | F1: Severity | G1: Priority | H1: Environment | I1: TC_ID | J1: Req_ID/US_ID | K1: Description | L1: Steps to Reproduce | M1: Expected Result | N1: Actual Result | O1: Status | P1: Assigned To | Q1: Detected By | R1: Date Logged | S1: Comments / Root Cause
A2: Bug_001 | B2: Authontication | C2: Logged-in user can open '/register' page via URL | D2: M_Atef | E2: v1.0 | F2: Critical | G2: High | H2: Windows 11 / Brave | I2: tc_008 | J2: FR-AUTH-01 | K2: Already logged-in users can manually access the registration page via direct URL instead of being automatically redirected to the dashboard. | L2: 1. While logged in, manually type the exact Registration URL in the browser's address bar and hit Enter. 2. Observe the system behavior and the loaded page. | M2: 1. Strictly blocks access to the registration form. 2. Automatically redirects the user back to their Home/Tenant Dashboard page smoothly. | N2: 1. The system allows access to the Registration page and renders the signup form despite the user having an active login session. | O2: New | P2: M_Kamel | Q2: M_Atef | R2: 2026-07-10
A3: Bug_002 | C3: Logged-in user can open '/login' page via URL | D3: M_Atef | E3: v1.0 | F3: Critical | G3: High | H3: Windows 11 / Brave | I3: tc_015 | J3: FR-AUTH-03 | K3: Already logged-in users can manually access the login page via direct URL instead of being automatically redirected to the dashboard | L3: 1. While logged in, manually type the exact Login URL in the browser's address bar and hit Enter. 2. Observe if the login form is displayed. | M3: 1. The login page is bypassed, and the user is automatically redirected straight to the active dashboard. | N3: 1. The system allows access to the Login page and renders the signin form despite the user having an active login session. | O3: New | P3: M_Kamel | Q3: M_Atef | R3: 2026-07-10
A4: Bug_003 | C4: 'Head' role is visible and allowed during registration code generation | D4: M_Atef | E4: v1.0 | F4: Critical | G4: High | H4: Windows 11 / Brave | I4: tc_025 | J4: FR-AUTH-06 | K4: In the "Generate Join Codes" section, the dropdown menu incorrectly displays the 'Head' role. The system allows generating a registration/enrollment code for a 'Head' account, which violates business logic since these codes are strictly for enrolling students. | L4: 1 .Navigate to the "Create Invitation Codes" section in the dashboard. 2. Open the Role Dropdown list to select the designated role for the new code 3. Select the 'Head' role and attempt to click the "Generate Code" button. | M4: 1. The 'Head' role must NOT be present in the dropdown list (Only Teacher, Student and Admin should be available). 2. [If selectable] The system blocks submission, rejects the request backend-side, and throws an error (e.g., "Cannot generate invitation code for Head role"). | N4: 1. The 'Head' role is visible and selectable in the dropdown list. 2. The system successfully generates an invitation code linked to the Head role. | O4: New | P4: M_Kamel | Q4: M_Atef | R4: 2026-07-10
A5: Bug_004 | C5: Tenant Admin can generate invitation codes for 'Admin' and 'Head' roles | D5: M_Atef | E5: v1.0 | F5: Critical | G5: High | H5: Windows 11 / Brave | I5: tc_030 | J5: Roles & Permmessions | K5: There is a flaw in role management permissions. The Tenant Admin is currently able to create invitation codes for administrative roles ('Admin' and 'Head'). According to business rules, admin privileges must only be granted internally by the Head account through role management, and these high-level roles should not be available for code generation. | L5: 1. Navigate to the "Invitation Codes" section inside the Admin Dashboard 2. Open the designated Role Dropdown list to choose which role this invitation code will grant upon registration. | M5: 1. The 'Admin' role must NOT be listed or available as an option in the dropdown (Only Teacher and Student should be selectable). | N5: 1. Admin can create Admin's codes and Head's codes | O5: New | P5: M_Kamel | Q5: M_Atef | R5: 2026-07-10
A6: Bug_005 | B6: Courses | C6: Teacher role is blocked from creating courses while Admin can create normally | D6: M_Atef | E6: v1.0 | F6: Critical | G6: High | H6: Windows 11 / Brave | I6: tc_033 | J6: FR-CRS-01 | K6: There is a critical permission block for the 'Teacher' role. Users logged in as a Teacher cannot create or add new courses on the platform. However, the creation flow works perfectly fine and normal when logged in as an Admin. | L6: 1. Click on the "Create Course" icon on the dashboard. 2. Enter valid course details and click Submit. | M6: 1. The course creation form opens successfully with fields: Title, Description, Cover Image, Subject, Price, and Sections. 2. The backend accepts the request, creates the database record, and a success message appears. | N6: 1. Course creation is blocked and appear an error message | O6: New | P6: M_Kamel | Q6: M_Atef | R6: 2026-07-10
A7: Bug_006 | C7: Subject dropdown is static and does not allow instructors to add custom subjects | D7: M_Atef | E7: v1.0 | F7: Critical | G7: High | H7: Windows 11 / Brave | I7: tc_034 | J7: FR-CRS-01 | K7: During course creation (Step 1), the "Subject" field is a fixed dropdown menu. Instructors are forced to select only from the pre-defined list and cannot manually type, edit, or add a custom subject of their own choice. | L7: 1. Navigate to the "Subject" field within the course creation form. 2. Attempt to type a new, unique subject name that does not exist in the initial list. | M7: 1. The field should either be a free-text input or a dynamic dropdown that includes an "Add New" or custom creation option. 2. The system accepts the typed input and registers it as the course's subject upon form submission. | N7: 1. The field is a rigid Dropdown menu containing only pre-defined options with no way to type custom text. 2. The dropdown blocks manual keyboard entry and restricts selection only to the old hardcoded list. | O7: New | P7: M_Kamel | Q7: M_Atef | R7: 2026-07-10
A8: Bug_007 | C8: Missing dedicated field for document attachments (Only Video URL field is available) | D8: M_Atef | E8: v1.0 | F8: Critical | G8: High | H8: Windows 11 / Brave | I8: tc_040 | J8: FR-CRS-03 | K8: During course creation (Step 2), there is no dedicated field or file picker to upload or link documents (like PDFs). The interface only provides fields for "Video Name" and "Video URL", forcing instructors to use the video field as a workaround for documents. | L8: 1. Open Step 2 (Sections & Videos) of the course wizard. 2. Inspect the form controls to see if PDF files can be uploaded or linked without reusing the video component | M8: 1. The page should display a clear, separate section, button, or input field dedicated to "Add Document" or "PDF Attachment" 2. Instructors can upload/link PDFs through an independent document container that applies file-specific UI icons.. | N8: 1. The only available input fields for lesson content are "Video Name" and "Video URL" 2. Instructors are forced to paste external PDF links into the Video URL field, causing icon mismatch. | O8: New | P8: M_Kamel | Q8: M_Atef | R8: 2026-07-10
A9: Bug_008 | C9: Draft courses are visible to other instructors instead of being private to the owner | D9: M_Atef | E9: v1.0 | F9: Critical | G9: High | H9: Windows 11 / Brave | I9: tc_043 | J9: FR-CRS-04 | K9: There is a data privacy bug in course visibility. When an instructor creates a course and sets it to Draft (Non-Public), the course is correctly hidden from students, but it is incorrectly visible to all other instructors on the platform. It should only be visible to the course owner, Admins, and Heads. | L9: 1. Log in with Teacher B (Non-Owner) credentials and navigate to the main Courses Dashboard | M9: The dashboard loads, but "Math Draft" MUST NOT be visible in Teacher B's course list or catalog. | N9: Math draft is appeared to teacher B's | O9: New | P9: M_Kamel | Q9: M_Atef | R9: 2026-07-10
A10: Bug_009 | B10: Question Bank – Search | C10: Whitespace-only search query is not trimmed and incorrectly returns an empty-state result | D10: Mahmoud Abdalazem | E10: v1.0 | F10: Low | G10: Medium | H10: Windows / Brave, Microsoft Edge (Latest) | I10: TC_QB_005 | J10: QB-005 | K10: The Question Bank Search field accepts whitespace-only input and processes it as a valid search instead of treating it as empty. | L10: 1. Log in as a Teacher. 2. Open the Question Bank page. 3. Enter only spaces (" ") in the Search field. 4. Click the Search button. 5. Observe the result. | M10: Spaces are trimmed automatically, or the input is treated as an empty search, without triggering an unexpected empty-state. | N10: The system treated the whitespace-only input as a valid query and displayed the "No Questions Found" message ("لم يتم العثور على أسئلة لا توجد بيانات"). | O10: New | P10: M_Kamel | Q10: Mahmoud Abdalazem | R10: 10-07-2026
A11: Bug_010 | B11: Question Bank – Question Details | C11: Question Details page shows raw untranslated i18n keys and a sticky header that overlaps the main content | D11: Mahmoud Abdalazem | E11: v1.0 | F11: High | G11: High | H11: Windows / Brave, Microsoft Edge (Latest) | I11: TC_QB_011 | J11: QB-011 | K11: The Question Details page displays untranslated i18n keys, and the sticky header overlaps the main question content during scrolling. | L11: 1. Log in as a Teacher. 2. Open the Question Bank page. 3. Select any question and click "View Details". 4. Observe the header labels. 5. Scroll down the page and observe the header behavior. | M11: The Question Details page opens displaying all available information without errors, with all labels properly localized. | N11: The labels "questions.back" and "questions.copyLink" are shown as raw translation keys instead of localized text, and the header remains sticky on scroll, overlapping and blocking the main question header. | O11: New | P11: M_Kamel | Q11: Mahmoud Abdalazem | R11: 10-07-2026
A12: Bug_011 | B12: Question Bank – Solve Question | C12: "Solve Question" incorrectly creates a persistent exam record instead of a preview, causing loss of prior selections/filters on return | D12: Mahmoud Abdalazem | E12: v1.0 | F12: High | G12: High | H12: Windows / Brave, Microsoft Edge (Latest) | I12: TC_QB_013, TC_QB_014 | J12: QB-013, QB-014 | K12: The "Solve Question" action creates a full exam instead of opening a preview, causing users to leave the Question Bank workflow and lose previously applied filters and selections upon return. | L12: 1. Log in as a Teacher. 2. Open the Question Bank page. 3. Click "Solve Question" on any question. 4. Observe the Exams page and open the newly created item. 5. Navigate back to the Question Bank via the sidebar. 6. Observe filters/selections. | M12: "Solve Question" opens a direct preview/solving page without affecting original question data or creating exam records; returning to the Question Bank preserves previously selected questions and applied filters. | N12: An isolated exam is created in the Exams page and opens as a full exam interface; returning to the Question Bank via the sidebar clears all previously applied filters and selections. | O12: New | P12: M_Kamel | Q12: Mahmoud Abdalazem | R12: 10-07-2026
A13: Bug_012 | B13: Question Bank – Question Selection | C13: Rapid repeated clicks on the (+) Add button cause an unstable add/remove loop instead of a single stable selection | D13: Mahmoud Abdalazem | E13: v1.0 | F13: Medium | G13: High | H13: Windows / Brave, Microsoft Edge (Latest) | I13: TC_QB_018 | J13: QB-018 | K13: The (+) Add button does not handle rapid repeated clicks correctly, causing the selected question to toggle between added and removed states instead of remaining selected. | L13: 1. Log in as a Teacher. 2. Open the Question Bank page. 3. Locate any question. 4. Click the (+) Add button several times quickly. 5. Observe the Selected Questions section and the selection counter. | M13: Only one instance of the question is added; no duplicate entries or UI instability occurs regardless of click speed. | N13: Rapid clicks cause the question to be repeatedly added and removed in sequence, producing an unstable UI state. | O13: New | P13: M_Kamel | Q13: Mahmoud Abdalazem | R13: 10-07-2026
A14: Bug_013 | B14: Question Bank – Selected Questions Panel | C14: No direct Remove/Delete control exists inside the Selected Questions panel | D14: Mahmoud Abdalazem | E14: v1.0 | F14: Medium | G14: High | H14: Windows / Brave, Microsoft Edge (Latest) | I14: TC_QB_019 | J14: QB-019 | K14: The Selected Questions panel lacks a direct Remove/Delete option, requiring users to return to the main question list to remove selected items. | L14: 1. Log in as a Teacher. 2. Open the Question Bank page. 3. Add one or more questions. 4. Go to the Selected Questions section. 5. Attempt to remove a question directly from this panel. | M14: The selected question is removed successfully from within the Selected Questions panel, and the counter decreases accordingly. | N14: No Remove/Delete button exists in the Selected Questions panel; removal is only possible via the main question list's delete icon. | O14: New | P14: M_Kamel | Q14: Mahmoud Abdalazem | R14: 10-07-2026
A15: Bug_014 | B15: Question Bank – Selected Questions Panel | C15: Selected Questions panel lacks scroll support, making questions beyond the fourth selection inaccessible | D15: Mahmoud Abdalazem | E15: v1.0 | F15: High | G15: High | H15: Windows / Brave, Microsoft Edge (Latest) | I15: TC_QB_036 | J15: QB-036 | K15: The Selected Questions panel does not provide scrolling, making additional selected questions inaccessible once the visible limit is exceeded. | L15: 1. Log in as a Teacher. 2. Open the Question Bank page. 3. Add 5 or more questions using the (+) Add button. 4. Observe the Selected Questions panel. 5. Attempt to scroll within the panel. | M15: A vertical scrollbar appears (or the panel expands), allowing access to all selected questions; no selection becomes inaccessible. | N15: After selecting more than four questions, additional selections become inaccessible because the panel provides no scrollbar. | O15: New | P15: M_Kamel | Q15: Mahmoud Abdalazem | R15: 10-07-2026
A16: Bug_015 | B16: Question Bank – Selected Questions Panel | C16: Long question text is truncated in the Selected Questions panel, breaking the layout | D16: Mahmoud Abdalazem | E16: v1.0 | F16: Low | G16: Medium | H16: Windows / Brave, Microsoft Edge (Latest) | I16: TC_QB_037 | J16: QB-037 | K16: Long question text is truncated in the Selected Questions panel instead of wrapping correctly, reducing readability. | L16: 1. Log in as a Teacher. 2. Open the Question Bank page. 3. Locate a question with long question text. 4. Click (+) to add it to the Selected Questions panel. 5. Observe how the text is displayed. | M16: The full question text wraps correctly within the panel without being cut off, overlapping other elements, or breaking the layout. | N16: The question text is truncated/cut off inside the panel, and the layout appears broken. | O16: New | P16: M_Kamel | Q16: Mahmoud Abdalazem | R16: 10-07-2026
A17: Bug_016 | B17: Question Bank – Filters | C17: Tag and Education Level filters incorrectly return "No Questions Found" despite matching questions existing | D17: Mahmoud Abdalazem | E17: v1.0 | F17: Critical | G17: High | H17: Windows / Brave, Microsoft Edge (Latest) | I17: TC_QB_038, TC_QB_039 | J17: QB-038, QB-039 | K17: Question Bank filters return "No Questions Found" despite matching questions existing, indicating incorrect filter logic. | L17: 1. Log in as a Teacher. 2. Open the Question Bank page. 3. Apply the "Free Response" tag filter, and separately apply a Levels filter (Preparatory Stage → Grade 1 → Mathematics). 4. Observe the displayed questions in each case. | M17: Only questions matching the selected tag or level hierarchy are displayed; an appropriate "No Questions Found" message is shown only when no matching data genuinely exists. | N17: Both filters return "No Questions Found / No Data" although matching questions exist for each. | O17: New | P17: M_Kamel | Q17: Mahmoud Abdalazem | R17: 10-07-2026
A18: Bug_017 | B18: Exam Creation – Instructions Field | C18: Instructions field fails to wrap long unbroken text strings, causing content to be visually cut off in student view | D18: Mahmoud Abdalazem | E18: v1.0 | F18: Low | G18: Medium | H18: Windows / Brave, Microsoft Edge (Latest) | I18: TC_EXM_046 | J18: FR-EXM-007 | K18: The Instructions field fails to wrap long continuous text, causing it to be truncated in the student view. | L18: 1. Log in as a Teacher. 2. Open the Create Exam page. 3. Paste a long continuous string of text without spaces (~1000 characters) into the Instructions field. 4. Complete remaining required fields and click Create Exam. 5. View the exam as a student. | M18: The complete text is accepted and displayed correctly without affecting page layout or functionality, regardless of spacing. | N18: Unbroken long text does not wrap and is severely truncated/visually inaccessible in the student view; text with normal spaces wraps correctly. | O18: New | P18: M_Kamel | Q18: Mahmoud Abdalazem | R18: 10-07-2026
A19: Bug_018 | B19: Exam Creation | C19: "Assign Class" field is not enforced as mandatory, allowing exam creation without a class selected | D19: Mahmoud Abdalazem | E19: v1.0 | F19: High | G19: High | H19: Windows / Brave, Microsoft Edge (Latest) | I19: TC_EXM_061 | J19: FR-EXM-022 | K19: The system allows exam creation without selecting an Assign Class, although the field is required. | L19: 1. Log in as a Teacher. 2. Open the Create Exam page. 3. Leave the "Assign Class" field empty. 4. Complete all remaining required fields. 5. Click Create Exam. 6. Observe the result. | M19: A validation message is displayed and the exam is not created; the user remains on the Create Exam page. | N19: The exam is created successfully despite no class being selected; no validation message is shown. | O19: New | P19: M_Kamel | Q19: Mahmoud Abdalazem | R19: 10-07-2026
A20: Bug_019 | B20: Exam Creation / Exams Dashboard | C20: Manually selected exam difficulty (Easy/Medium/Hard) is overridden by a dynamically calculated value on the Exams page | D20: Mahmoud Abdalazem | E20: v1.0 | F20: Medium | G20: Medium | H20: Windows / Brave, Microsoft Edge (Latest) | I20: TC_EXM_062, TC_EXM_063, TC_EXM_064 | J20: FR-EXM-023, FR-EXM-024, FR-EXM-025 | K20: The manually selected exam difficulty is ignored, and the system displays a calculated difficulty based on question levels. | L20: 1. Log in as a Teacher. 2. Open the Create Exam page. 3. Select a difficulty level (Easy, Medium, or Hard) from the Difficulty dropdown. 4. Complete remaining required fields and click Create Exam. 5. Open the Exams page and check the displayed difficulty. | M20: The exam is created and the difficulty selected during creation (Easy, Medium, or Hard) is saved and displayed as-is on the Exams page. | N20: The Exams page overrides the manually selected difficulty and instead displays a value computed from the selected questions' levels, for all three difficulty options. | O20: New | P20: M_Kamel | Q20: Mahmoud Abdalazem | R20: 10-07-2026
A21: Bug_020 | B21: Exam Creation – Override Rules | C21: Override Rule can be added with empty required fields, bypassing validation | D21: Mahmoud Abdalazem | E21: v1.0 | F21: High | G21: High | H21: Windows / Brave, Microsoft Edge (Latest) | I21: TC_EXM_071 | J21: FR-EXM-032 | K21: The system allows exam creation with empty required Override Rule fields without displaying validation messages. | L21: 1. Log in as a Teacher. 2. Open the Create Exam page. 3. Click "Add Rule". 4. Leave the required fields of the rule empty. 5. Click Create Exam. 6. Observe the result. | M21: Appropriate validation messages are displayed and the exam is not created until valid values are entered into the Override Rule fields. | N21: The system accepts the exam creation with empty Override Rule fields; no validation message is displayed. | O21: New | P21: M_Kamel | Q21: Mahmoud Abdalazem | R21: 10-07-2026
... A24: Bug_023 | B24: Exam Management – Deleted Exam Access | C24: Test execution for deleted-exam direct access control recorded as Failed | D24: Mahmoud Abdalazem | E24: v1.0 | F24: High | G24: High | H24: Windows / Brave, Microsoft Edge (Latest) | I24: TC_EXM_107 | J24: FR-EXM-068 | K24: The test case is marked as Failed, but the recorded Actual Result indicates successful behavior, creating an inconsistency that requires re-verification. | L24: 1. Log in as Teacher/Admin. 2. Delete an existing exam. 3. Navigate directly to the deleted exam's URL. 4. Observe the system response. | M24: The system displays an appropriate error message or redirects the user instead of loading the deleted exam. | N24: As recorded in the test sheet: "The system functions as expected and all related actions were verified successfully." (Status logged as Fail; the recorded actual-result text does not specify what, if anything, deviated from expected behavior.) | O24: New | P24: M_Kamel | Q24: Mahmoud Abdalazem | R24: 10-07-2027
A25: Bug_024 | B25: Plan Selection | C25: Duplicate "Teacher" package card displayed under Basic Plan | D25: Abdelhamid Anwer | F25: Low | G25: Medium | H25: TC-01 | I25: UI | J25: The Basic subscription plan displays two identical Teacher package cards, causing UI inconsistency and user confusion. | K25: 1. Open Pricing page. 2. Navigate to Basic Plan. 3. Observe available packages. | L25: Only one Teacher package card should be displayed under the Basic plan. | M25: Two identical Teacher package cards are displayed. | N25: New | P25: New | Q25: M_Kamel | R25: Abdelhamid Anwer | S25: 46213
A26: Bug_025 | B26: Billing | C26: Payment code can be redeemed more than once | D26: Abdelhamid Anwer | F26: Critical | G26: High | H26: TC-15 | I26: FR-BAL-04 | J26: The system allows an already redeemed payment code to be redeemed again. | K26: 1. Login as Head/Admin. 2. Redeem a valid payment code. 3. Redeem the same code again. | L26: Second redemption should be rejected and balance unchanged. | M26: Code is accepted again and balance increases. | N26: New | P26: New | Q26: M_Kamel | R26: Abdelhamid Anwer | S26: 46213
A27: Bug_026 | B27: Billing | C27: Student payment redemption does not update tenant balance | D27: Abdelhamid Anwer | F27: Critical | G27: High | H27: TC-20 | I27: FR-BAL-02 | J27: Student redemption does not credit tenant balance. | K27: 1. Login as Student. 2. Redeem a valid code. 3. Check tenant balance. | L27: Balance should increase and payment become Redeemed. | M27: Payment is Redeemed but balance is unchanged. | N27: New | P27: New | Q27: M_Kamel | R27: Abdelhamid Anwer | S27: 46213
A28: Bug_027 | B28: Billing | C28: Invalid payment code is accepted | D28: Abdelhamid Anwer | F28: High | G28: High | H28: TC-25 | I28: FR-BAL-03 | J28: Invalid payment code is processed successfully. | K28: 1. Login. 2. Enter invalid code. 3. Click Redeem. | L28: Code should be rejected. | M28: Invalid code is accepted. | N28: New | P28: New | Q28: M_Kamel | R28: Abdelhamid Anwer | S28: 46213
A29: Bug_028 | B29: Tenant Onboarding | C29: Duplicate subdomain is accepted | D29: Abdelhamid Anwer | F29: Critical | G29: High | H29: TC-30 | I29: FR-BAL-11 | J29: Duplicate subdomain allowed. | K29: 1. Register institution. 2. Enter existing subdomain. 3. Submit. | L29: Duplicate subdomain should be rejected. | M29: Institution created successfully. | N29: New | P29: New | Q29: M_Kamel | R29: Abdelhamid Anwer | S29: 46213
A30: Bug_029 | B30: Billing | C30: Withdrawal rejection allows empty rejection reason | D30: Abdelhamid Anwer | F30: Medium | G30: Medium | H30: TC-35 | I30: FR-BAL-08 | J30: Superuser can reject without reason. | K30: 1. Open pending request. 2. Reject with empty reason. | L30: Reason should be mandatory. | M30: Request rejected without reason. | N30: New | P30: New | Q30: M_Kamel | R30: Abdelhamid Anwer | S30: 46213
A31: Bug_030 | B31: Subscription | C31: Subscription downgrade ignores current usage limits | D31: Abdelhamid Anwer | F31: Critical | G31: Critical | H31: TC-45 | I31: FR-SUB-03 | J31: Downgrade allowed although usage exceeds limits. | K31: 1. Exceed plan limits. 2. Downgrade. | L31: Downgrade should be rejected. | M31: Downgrade succeeds. | N31: New | P31: New | Q31: M_Kamel | R31: Abdelhamid Anwer | S31: 46213
A32: Bug_031 | B32: Subscription | C32: Renewal calculates incorrect expiry date | D32: Abdelhamid Anwer | F32: High | G32: High | H32: TC-50 | I32: FR-SUB-04 | J32: Incorrect renewal date calculation. | K32: 1. Renew subscription. 2. Verify expiry. | L32: Expiry = previous end + cycle + 7-day buffer. | M32: Incorrect expiry date. | N32: New | P32: New | Q32: M_Kamel | R32: Abdelhamid Anwer | S32: 46213
A33: Bug_032 | B33: Subscription | C33: Pending Renewal not triggered 7 days before expiry | D33: Abdelhamid Anwer | F33: High | G33: High | H33: TC-55 | I33: FR-SUB-07 | J33: Status remains Active. | K33: 1. Set expiry to 7 days. 2. Run scheduler. | L33: Status changes to Pending Renewal and email sent. | M33: Status remains Active. | N33: New | P33: New | Q33: M_Kamel | R33: Abdelhamid Anwer | S33: 46213
A34: BUG-033 | B34: Landing Page Sections - Admin (Create Section Form) | C34: Display Order field defaults to 1 and blocks empty-value validation testing | D34: QA Engineer | E34: Regression Testing Cycle | F34: Low | G34: Low | H34: Web - Staging/UAT | I34: LPS-08 | K34: The Display Order field cannot be cleared to an empty value, preventing verification of the required-field validation. | L34: 1. Open the Create Section form. 2. Attempt to clear the 'ترتيب العرض' (Display Order) field. 3. Try to submit the form. | M34: Form shows an error and does not save when Display Order is left empty. | N34: Display Order field cannot be cleared/emptied; it defaults to 1, so the empty-field validation cannot be triggered or verified. | O34: Open | P34: Developer | Q34: M_Kamel | R34: 10-07-2026
A35: BUG-034 | B35: Landing Page Sections - Admin (Create Section Form) | C35: 'Add Card' button throws an error when an existing card is left empty | D35: QA Engineer | E35: Regression Testing Cycle | F35: Medium | G35: Medium | H35: Web - Staging/UAT | I35: LPS-11 | K35: Clicking 'Add Card' while an existing card has empty fields throws an error instead of adding a new card. | L35: 1. Open the Create Section form. 2. Leave the existing card's fields empty. 3. Click 'إضافة بطاقة' (Add Card). | M35: A new empty card box is added below the existing one. | N35: An error is thrown when attempting to add a card while the existing card is empty. | O35: Open | P35: Developer | Q35: M_Kamel | R35: 10-07-2026
A36: BUG-035 | B36: Landing Page Sections - Admin (Create Section Form) | C36: Card order arrows not disabled when only one card exists | D36: QA Engineer | E36: Regression Testing Cycle | F36: Low | G36: Low | H36: Web - Staging/UAT | I36: LPS-13 | K36: The card reorder (up/down) buttons remain enabled and clickable even when only one card exists in the section form. | L36: 1. Open the Create Section form. 2. Ensure only 1 card exists in the form. 3. Check the state of the up/down arrow buttons on the card. | M36: Both up and down arrows are disabled (greyed out) when only 1 card exists. | N36: The up/down arrows remain active and the card can be reordered even though only one card is present. | O36: Open | P36: Developer | Q36: M_Kamel | R36: 10-07-2026
A37: BUG-036 | B37: Subscription - Usage Numbers | C37: Current Users count incorrect after subscription renewal | D37: QA Engineer | E37: Regression Testing Cycle | F37: High | G37: High | H37: Web - Staging/UAT | I37: SUB-05 | K37: The 'Current Users' count on the Subscription tab does not correctly reflect the actual number of users after a subscription renewal. | L37: 1. Note the real user count in the Users tab. 2. Go to the Subscription tab and renew the subscription. 3. Check the 'المستخدمون الحاليون' (Current Users) number again. | M37: The Current Users number should still correctly reflect the real number of users after renewal. | N37: Current Users count does not correctly reflect the real user count after renewal (known bug area). | O37: Open | P37: Developer | Q37: M_Kamel | R37: 10-07-2026
A38: BUG-037 | B38: Subscription - Usage Numbers | C38: Missing feedback message when renewing an already-active subscription | D38: QA Engineer | E38: Regression Testing Cycle | F38: Low | G38: Medium | H38: Web - Staging/UAT | I38: REN-02 | K38: No confirmation or informational message is displayed when a user attempts to renew an already-active subscription. | L38: 1. Ensure the subscription is still active (not expired). 2. Click 'تجديد الاشتراك' (Renew Subscription). | M38: A clear success/informational message should be shown when Renew is clicked while the subscription is active. | N38: No message is displayed indicating the user is already subscribed; no feedback is given to the user. | O38: Open | P38: Developer | Q38: M_Kamel | R38: 10-07-2026
A39: BUG-038 | B39: Subscription - Usage Numbers | C39: Expired subscription status/message not displayed correctly | D39: QA Engineer | E39: Regression Testing Cycle | F39: High | G39: High | H39: Web - Staging/UAT | I39: REN-03, REN-08 | K39: The system does not clearly indicate that a subscription has expired, both when it first reaches its end date and after refreshing the page with no renewal action taken. | L39: 1. Let a subscription reach its end date (or use a test account close to expiry). 2. Observe whether an expiration message is shown. 3. Without renewing, refresh the page and observe the displayed subscription status. | M39: System should clearly show a message that the subscription has ended, and the page should continue to clearly indicate expired status until the user renews. | N39: No message shows when the subscription reaches its end date; expired status is not clearly indicated after a page refresh with no renewal action. | O39: Open | P39: Developer | Q39: M_Kamel | R39: 10-07-2026
A40: BUG-039 | B40: Exams - Creation | C40: Exam creation accepts zero/negative duration | D40: Hamza Musallam | E40: Exams Module - Test Cycle 1 | F40: Medium | G40: Medium | H40: Web - https://zakerai.org/ (TBC: browser/OS/device) | I40: EC-03 | J40: N/A | K40: Duration field does not validate for zero/negative values, allowing an exam with an invalid duration to be created. | L40: 1. Go to 'Create Exam' page 2. Fill in all required fields 3. Enter duration = 0 or a negative number (e.g. -10) 4. Click 'Save' / 'Create' | M40: Validation error is displayed; exam creation is blocked | N40: No validation error is shown for duration = 0 or a negative value; the exam appears to be saved/created | O40: Open | P40: Unassigned | Q40: Hamza Musallam | R40: 46213 | S40: TBC by developer/QA during triage
A41: BUG-040 | B41: Exams - Creation | C41: Removed question still included after saving the exam | D41: Hamza Musallam | E41: Exams Module - Test Cycle 1 | F41: Medium | G41: Medium | H41: Web - https://zakerai.org/ (TBC: browser/OS/device) | I41: EC-05 | J41: N/A | K41: Removing a question during exam creation is not persisted correctly when the exam is saved. | L41: 1. Go to 'Create Exam' page 2. Add 5 questions to the exam 3. Remove 1 of the added questions 4. Save the exam | M41: Only the remaining 4 questions are included in the saved exam | N41: The saved exam does not reflect the removal; the removed question is still present (or the question count is incorrect) after saving | O41: Open | P41: Unassigned | Q41: Hamza Musallam | R41: 46213 | S41: TBC by developer/QA during triage
A42: BUG-041 | B42: Exams - Creation | C42: Duplicate exam name handling is inconsistent / undefined | D42: Hamza Musallam | E42: Exams Module - Test Cycle 1 | F42: Low | G42: Low | H42: Web - https://zakerai.org/ (TBC: browser/OS/device) | I42: EC-07 | J42: N/A | K42: No defined or consistent behavior for duplicate exam names; needs a product decision and consistent implementation. | L42: 1. Create a new exam using the exact same name as an existing exam 2. Attempt to save | M42: System either warns about duplicate names or allows it per a documented, consistent design | N42: Behavior is inconsistent/unclear — no warning is shown and no documented rule could be confirmed | O42: Open | P42: Unassigned | Q42: Hamza Musallam | R42: 46213 | S42: TBC by developer/QA during triage
A43: BUG-042 | B43: Exams - Creation | C43: Answer-choice shuffle breaks correct-answer mapping for MCQ questions | D43: Hamza Musallam | E43: Exams Module - Test Cycle 1 | F43: High | G43: Medium | H43: Web - https://zakerai.org/ (TBC: browser/OS/device) | I43: EC-12 | J43: N/A | K43: Shuffle-answers feature does not correctly remap the correct answer, resulting in incorrect auto-grading. | L43: 1. Enable 'Shuffle answer choices' on an exam containing MCQ questions 2. Save and publish 3. Have two different students take the exam and compare answer order and scoring | M43: Answer choice order differs between students while the correct-answer mapping remains accurate | N43: Answer order is shuffled, but the correct-answer mapping does not follow the shuffle, causing incorrect grading of MCQ answers | O43: Open | P43: Unassigned | Q43: Hamza Musallam | R43: 46213 | S43: TBC by developer/QA during triage
A44: BUG-043 | B44: Exams - Creation | C44: Duplicating/cloning an exam does not create an independent copy | D44: Hamza Musallam | E44: Exams Module - Test Cycle 1 | F44: Medium | G44: Low | H44: Web - https://zakerai.org/ (TBC: browser/OS/device) | I44: EC-19 | J44: N/A | K44: Exam duplication/cloning does not fully decouple the copy from the source exam. | L44: 1. Select an existing exam 2. Click 'Duplicate' / 'Clone' 3. Rename and adjust the copy, then save | M44: A new independent exam is created with the same questions/settings as the source, editable without affecting the original | N44: Cloned exam is not fully independent — editing the copy appears to affect the original exam, or the clone is missing questions/settings | O44: Open | P44: Unassigned | Q44: Hamza Musallam | R44: 46213 | S44: TBC by developer/QA during triage
A45: BUG-044 | B45: Exams - Creation | C45: Allowed-attempts limit is not enforced | D45: Hamza Musallam | E45: Exams Module - Test Cycle 1 | F45: High | G45: Medium | H45: Web - https://zakerai.org/ (TBC: browser/OS/device) | I45: EC-20 | J45: N/A | K45: Attempt-limit configuration is not enforced server-side, allowing unlimited attempts. | L45: 1. Set 'Allowed attempts' to a specific number (e.g. 2) 2. Save/publish the exam 3. Have a student attempt the exam more times than allowed | M45: Student can attempt up to the configured limit; further attempts are blocked with a clear message | N45: Student is able to start additional attempts beyond the configured limit; no blocking message is shown | O45: Open | P45: Unassigned | Q45: Hamza Musallam | R45: 46213 | S45: TBC by developer/QA during triage
A46: BUG-045 | B46: Exams - Creation | C46: Pass/Fail status does not correctly reflect the configured passing score | D46: Hamza Musallam | E46: Exams Module - Test Cycle 1 | F46: High | G46: Medium | H46: Web - https://zakerai.org/ (TBC: browser/OS/device) | I46: EC-21 | J46: N/A | K46: Pass/Fail evaluation logic does not correctly apply the configured passing-score threshold. | L46: 1. Set a passing score (e.g. 60%) 2. Publish the exam 3. Submit exam attempts above and below the threshold | M46: Results correctly reflect Pass/Fail status based on the configured threshold | N46: Pass/Fail status shown in results does not match the configured threshold (e.g. a below-threshold score is marked as Pass, or vice versa) | O46: Open | P46: Unassigned | Q46: Hamza Musallam | R46: 46213 | S46: TBC by developer/QA during triage
A47: BUG-046 | B47: Exams - Creation | C47: Exam not available to all classes/groups when assigned to multiple groups at once | D47: Hamza Musallam | E47: Exams Module - Test Cycle 1 | F47: Medium | G47: Medium | H47: Web - https://zakerai.org/ (TBC: browser/OS/device) | I47: EC-22 | J47: N/A | K47: Multi-group assignment does not propagate exam visibility to all selected classes/groups. | L47: 1. Create an exam 2. Assign it to more than one class/group 3. Save/publish | M47: The exam becomes available to students in all assigned classes/groups | N47: The exam is only available to one of the assigned groups; students in the other assigned group(s) cannot see/access it | O47: Open | P47: Unassigned | Q47: Hamza Musallam | R47: 46213 | S47: TBC by developer/QA during triage
A48: BUG-047 | B48: Exams - Creation | C48: Exam schedule not correctly converted across time zones | D48: Hamza Musallam | E48: Exams Module - Test Cycle 1 | F48: Low | G48: Low | H48: Web - https://zakerai.org/ (TBC: browser/OS/device) | I48: EC-23 | J48: N/A | K48: Exam start/end times are not correctly converted between teacher and student time zones. | L48: 1. Create an exam with a start/end date-time as the teacher 2. Log in as a student in a different time zone and check the displayed exam schedule | M48: The exam's start/end time is displayed correctly, converted to each user's local time zone | N48: The displayed start/end time for the student is not correctly converted to their local time zone | O48: Open | P48: Unassigned | Q48: Hamza Musallam | R48: 46213 | S48: TBC by developer/QA during triage
A49: BUG-048 | B49: Exams - Submission | C49: Submitted exam attempt can be reopened and resubmitted/edited | D49: Hamza Musallam | E49: Exams Module - Test Cycle 1 | F49: High | G49: High | H49: Web - https://zakerai.org/ (TBC: browser/OS/device) | I49: ES-04 | J49: N/A | K49: Submission-lock logic does not prevent edits/resubmission of an already-submitted exam attempt. | L49: 1. Submit an exam attempt as a student 2. Attempt to reopen the same exam attempt 3. Attempt to change answers or resubmit | M49: System blocks further edits/submission and shows an appropriate message (e.g. 'Exam already submitted') | N49: The already-submitted attempt can be reopened and answers can be changed/resubmitted, with no blocking message shown | O49: Open | P49: Unassigned | Q49: Hamza Musallam | R49: 46213 | S49: TBC by developer/QA during triage
A50: BUG-049 | B50: Exams - Submission | C50: Loss of network connection during submission risks losing student answers | D50: Hamza Musallam | E50: Exams Module - Test Cycle 1 | F50: High | G50: High | H50: Web - https://zakerai.org/ (TBC: browser/OS/device) | I50: ES-06 | J50: N/A | K50: No resilient retry/recovery handling for network loss during final submission. | L50: 1. Start submitting an exam 2. Disable the network connection immediately after clicking 'Submit' 3. Restore connection and check the attempt/answers | M50: System retries or shows a clear error message without losing the student's answers; student is able to resubmit once connection is restored | N50: No clear error/retry is shown, and the student's answers/submission appear to be lost or left in an inconsistent state after the connection is restored | O50: Open | P50: Unassigned | Q50: Hamza Musallam | R50: 46213 | S50: TBC by developer/QA during triage
A51: BUG-050 | B51: Exams - Submission | C51: Second exam attempt not scored per the configured multiple-attempts rule | D51: Hamza Musallam | E51: Exams Module - Test Cycle 1 | F51: Medium | G51: Medium | H51: Web - https://zakerai.org/ (TBC: browser/OS/device) | I51: ES-14 | J51: N/A | K51: Scoring logic for multiple allowed attempts does not correctly apply the configured best/latest-attempt rule. | L51: 1. Complete and submit a first exam attempt 2. Start a second attempt 3. Complete and submit the second attempt | M51: Both attempts are recorded; the final displayed score follows the configured rule (e.g. best attempt or latest attempt) | N51: The displayed final score does not follow the configured rule (e.g. wrong attempt's score is shown, or only one attempt is recorded) | O51: Open | P51: Unassigned | Q51: Hamza Musallam | R51: 46213 | S51: TBC by developer/QA during triage
... A55: BUG-054 | B55: Exams - Submission | C55: Bulk exported exam results (CSV/Excel) do not match the on-screen results | D55: Hamza Musallam | E55: Exams Module - Test Cycle 1 | F55: Medium | G55: Medium | H55: Web - https://zakerai.org/ (TBC: browser/OS/device) | I55: ES-23 | J55: N/A | K55: Bulk export feature produces a file that is inconsistent with the on-screen results/grades data. | L55: 1. Open the exam's results/grades page 2. Click 'Export' and choose a format (e.g. CSV/Excel) 3. Open the exported file and compare to the on-screen results | M55: An accurate file is downloaded containing all student names, scores, and submission statuses matching what's shown on screen | N55: The exported file is missing data, contains incorrect values, or does not match what's displayed on the results page | O55: Open | P55: Unassigned | Q55: Hamza Musallam | R55: 46213 | S55: TBC by developer/QA during triage

Sheet Traceability
A1: Req_ID | B1: Module | C1: Priority | D1: Linked_TestCases | E1: TC_Count | F1: Passed | G1: Failed | H1: Blocked | I1: Not_Executed | J1: Coverage_Status | K1: Bug_Count
A2: FR-AUTH-01 | B2: Auth | C2: P1 | D2: =_xlfn.TEXTJOIN(", ",TRUE,IF(Test_Cases!$C$2:$C$368=A2,Test_Cases!$A$2:$A$368,"")) -> tc_001, tc_002, tc_003, tc_004, tc_005, tc_006, tc_007, tc_008, tc_009, tc_010, tc_011, tc_012, tc_013, tc_014, tc_015, tc_016, tc_017, tc_018, tc_019, tc_020, tc_021, tc_022, tc_023, tc_024, tc_025, tc_026, tc_027, tc_028, tc_029, tc_030, tc_031, tc_032, tc_033, tc_034, tc_035, tc_036, tc_037, tc_038, tc_039, tc_040, tc_041, tc_042, tc_043, tc_044, tc_045, tc_046, tc_047, TC_QB_001, TC_QB_002, TC_QB_003, TC_QB_004, TC_QB_005, TC_QB_006, TC_QB_007, TC_QB_008, TC_QB_009, TC_QB_010, TC_QB_011, TC_QB_012, TC_QB_013, TC_QB_014, TC_QB_015, TC_QB_016, TC_QB_017, TC_QB_018, TC_QB_019, TC_QB_020, TC_QB_021, TC_QB_022, TC_QB_023, TC_QB_024, TC_QB_025, TC_QB_026, TC_QB_027, TC_QB_028, TC_QB_029, TC_QB_030, TC_QB_031, TC_QB_032, TC_QB_033, TC_QB_034, TC_QB_035, TC_QB_036, TC_QB_037, TC_QB_038, TC_QB_039, TC_EXM_040, TC_EXM_041, TC_EXM_042, TC_EXM_043, TC_EXM_044, TC_EXM_045, TC_EXM_046, TC_EXM_047, TC_EXM_048, TC_EXM_049, TC_EXM_050, TC_EXM_051, TC_EXM_052, TC_EXM_053, TC_EXM_054, TC_EXM_055, TC_EXM_056, TC_EXM_057, TC_EXM_058, TC_EXM_059, TC_EXM_060, TC_EXM_061, TC_EXM_062, TC_EXM_063, TC_EXM_064, TC_EXM_065, TC_EXM_066, TC_EXM_067, TC_EXM_068, TC_EXM_069, TC_EXM_070, TC_EXM_071, TC_EXM_072, TC_EXM_073, TC_EXM_074, TC_EXM_075, TC_EXM_076, TC_EXM_077, TC_EXM_078, TC_EXM_079, TC_EXM_080, TC_EXM_081, TC_EXM_082, TC_EXM_083, TC_EXM_084, TC_EXM_085, TC_EXM_086, TC_EXM_087, TC_EXM_088, TC_EXM_089, TC_EXM_090, TC_EXM_091, TC_EXM_092, TC_EXM_093, TC_EXM_094, TC_EXM_095, TC_EXM_096, TC_EXM_097, TC_EXM_098, TC_EXM_099, TC_EXM_100, TC_EXM_101, TC_EXM_102, TC_EXM_103, TC_EXM_104, TC_EXM_105, TC_EXM_106, TC_EXM_107, TC_EXM_108, TC_EXM_109, TC_EXM_110, tc-01, tc-02, tc-03, tc-04, tc-05, tc-06, tc-07, tc-08, tc-10, tc-11, tc-12, tc-13, tc-14, tc-15, tc-16, tc-17, tc-18, tc-19, tc-20, tc-21, tc-22, tc-23, tc-24, tc-25, tc-26, tc-27, tc-28, tc-29, tc-30, tc-31, tc-32, tc-33, tc-34, tc-35, tc-36, tc-37, tc-38, tc-39, tc-40, tc-41, tc-42, tc-43, tc-44, tc-45, tc-46, tc-47, tc-48, tc-49, tc-50, tc-51, tc-52, tc-53, tc-54, tc-55, tc-56, tc-57, tc-58, tc-59, tc-60, tc-61, tc-62, tc-63, tc-64, tc-65, tc-66, tc-67, tc-68, tc-69, tc-70, tc-71, tc-72, tc-73, tc-74, tc-75, tc-76, tc-77, tc-78, tc-79, tc-80, tc-81, tc-82, tc-83, tc-84, tc-85, tc-86, tc-87, EC-01, EC-02, EC-03, EC-04, EC-05, EC-06, EC-07, EC-08, EC-09, EC-10, EC-11, EC-12, EC-13, EC-14, EC-15, EC-16, EC-17, EC-18, EC-19, EC-20, EC-21, EC-22, EC-23, EC-24, ES-01, ES-02, ES-03, ES-04, ES-05, ES-06, ES-07, ES-08, ES-09, ES-10, ES-11, ES-12, ES-13, ES-14, ES-15, ES-16, ES-17, ES-18, ES-19, ES-20, ES-21, ES-22, ES-23, LPS-01, LPS-02, LPS-03, LPS-04, LPS-05, LPS-06, LPS-07, LPS-08, LPS-09, LPS-10, LPS-11, LPS-12, LPS-13, LPS-14, LPS-15, LPS-16, LPS-17, LPS-18, LPS-19, LPS-20, LPS-21, LPS-22, LPS-23, LPS-24, LPS-25, LPS-26, LPS-27, LPS-28, LPF-01, LPF-02, LPF-03, LPF-04, LPF-05, LPF-06, LPF-07, LPF-08, LPF-09, LPF-10, SUB-01, SUB-02, SUB-03, SUB-04, SUB-05, SUB-06, SUB-07, SUB-08, REN-01, REN-02, REN-03, REN-04, REN-05, REN-07, REN-08, CQ-01, CQ-02, CQ-03, CQ-04, CQ-05, CQ-06, CQ-07, CQ-08, CQ-09, CQ-10, CQ-11, CQ-12, CQ-13, CQ-14, CQ-15, CQ-16, CQ-17, CQ-18, CQ-19, CQ-20, CQ-21, CQ-22, CQ-23, CQ-24 | E2: =COUNTIF(Test_Cases!$C$2:$C$368,A2) -> 8 | F2: =COUNTIFS(Test_Cases!$C$2:$C$368,A2,Test_Cases!$L$2:$L$368,"Passed") -> 7 | G2: =COUNTIFS(Test_Cases!$C$2:$C$368,A2,Test_Cases!$L$2:$L$368,"Failed") -> 1 | H2: =COUNTIFS(Test_Cases!$C$2:$C$368,A2,Test_Cases!$L$2:$L$368,"Blocked") -> 0 | I2: =COUNTIFS(Test_Cases!$C$2:$C$368,A2,Test_Cases!$L$2:$L$368,"Not_Executed") -> 0 | J2: =IF(E2=0,"Not Covered",IF(G2>0,"Failing",IF(F2=E2,"Fully Covered","Partial"))) -> Failing | K2: =COUNTIF(Bug_Report!$J$2:$J$55,"*"&A2&"*") -> 1
A3: FR-AUTH-02 | B3: Auth | C3: P1 | D3: =_xlfn.TEXTJOIN(", ",TRUE,IF(Test_Cases!$C$2:$C$368=A3,Test_Cases!$A$2:$A$368,"")) | E3: =COUNTIF(Test_Cases!$C$2:$C$368,A3) -> 2 | F3: =COUNTIFS(Test_Cases!$C$2:$C$368,A3,Test_Cases!$L$2:$L$368,"Passed") -> 2 | G3: =COUNTIFS(Test_Cases!$C$2:$C$368,A3,Test_Cases!$L$2:$L$368,"Failed") -> 0 | H3: =COUNTIFS(Test_Cases!$C$2:$C$368,A3,Test_Cases!$L$2:$L$368,"Blocked") -> 0 | I3: =COUNTIFS(Test_Cases!$C$2:$C$368,A3,Test_Cases!$L$2:$L$368,"Not_Executed") -> 0 | J3: =IF(E3=0,"Not Covered",IF(G3>0,"Failing",IF(F3=E3,"Fully Covered","Partial"))) -> Fully Covered | K3: =COUNTIF(Bug_Report!$J$2:$J$55,"*"&A3&"*") -> 0
A4: FR-AUTH-03 | B4: Auth | C4: P1 | D4: =_xlfn.TEXTJOIN(", ",TRUE,IF(Test_Cases!$C$2:$C$368=A4,Test_Cases!$A$2:$A$368,"")) | E4: =COUNTIF(Test_Cases!$C$2:$C$368,A4) -> 5 | F4: =COUNTIFS(Test_Cases!$C$2:$C$368,A4,Test_Cases!$L$2:$L$368,"Passed") -> 4 | G4: =COUNTIFS(Test_Cases!$C$2:$C$368,A4,Test_Cases!$L$2:$L$368,"Failed") -> 1 | H4: =COUNTIFS(Test_Cases!$C$2:$C$368,A4,Test_Cases!$L$2:$L$368,"Blocked") -> 0 | I4: =COUNTIFS(Test_Cases!$C$2:$C$368,A4,Test_Cases!$L$2:$L$368,"Not_Executed") -> 0 | J4: =IF(E4=0,"Not Covered",IF(G4>0,"Failing",IF(F4=E4,"Fully Covered","Partial"))) -> Failing | K4: =COUNTIF(Bug_Report!$J$2:$J$55,"*"&A4&"*") -> 1
A5: FR-AUTH-04 | B5: Auth | C5: P1 | D5: =_xlfn.TEXTJOIN(", ",TRUE,IF(Test_Cases!$C$2:$C$368=A5,Test_Cases!$A$2:$A$368,"")) | E5: =COUNTIF(Test_Cases!$C$2:$C$368,A5) -> 5 | F5: =COUNTIFS(Test_Cases!$C$2:$C$368,A5,Test_Cases!$L$2:$L$368,"Passed") -> 1 | G5: =COUNTIFS(Test_Cases!$C$2:$C$368,A5,Test_Cases!$L$2:$L$368,"Failed") -> 0 | H5: =COUNTIFS(Test_Cases!$C$2:$C$368,A5,Test_Cases!$L$2:$L$368,"Blocked") -> 0 | I5: =COUNTIFS(Test_Cases!$C$2:$C$368,A5,Test_Cases!$L$2:$L$368,"Not_Executed") -> 4 | J5: =IF(E5=0,"Not Covered",IF(G5>0,"Failing",IF(F5=E5,"Fully Covered","Partial"))) -> Partial | K5: =COUNTIF(Bug_Report!$J$2:$J$55,"*"&A5&"*") -> 0
A6: FR-AUTH-05 | B6: Auth | C6: P1 | D6: =_xlfn.TEXTJOIN(", ",TRUE,IF(Test_Cases!$C$2:$C$368=A6,Test_Cases!$A$2:$A$368,"")) | E6: =COUNTIF(Test_Cases!$C$2:$C$368,A6) -> 1 | F6: =COUNTIFS(Test_Cases!$C$2:$C$368,A6,Test_Cases!$L$2:$L$368,"Passed") -> 0 | G6: =COUNTIFS(Test_Cases!$C$2:$C$368,A6,Test_Cases!$L$2:$L$368,"Failed") -> 0 | H6: =COUNTIFS(Test_Cases!$C$2:$C$368,A6,Test_Cases!$L$2:$L$368,"Blocked") -> 0 | I6: =COUNTIFS(Test_Cases!$C$2:$C$368,A6,Test_Cases!$L$2:$L$368,"Not_Executed") -> 1 | J6: =IF(E6=0,"Not Covered",IF(G6>0,"Failing",IF(F6=E6,"Fully Covered","Partial"))) -> Partial | K6: =COUNTIF(Bug_Report!$J$2:$J$55,"*"&A6&"*") -> 0
A7: FR-AUTH-06 | B7: Auth | C7: P1 | D7: =_xlfn.TEXTJOIN(", ",TRUE,IF(Test_Cases!$C$2:$C$368=A7,Test_Cases!$A$2:$A$368,"")) | E7: =COUNTIF(Test_Cases!$C$2:$C$368,A7) -> 4 | F7: =COUNTIFS(Test_Cases!$C$2:$C$368,A7,Test_Cases!$L$2:$L$368,"Passed") -> 3 | G7: =COUNTIFS(Test_Cases!$C$2:$C$368,A7,Test_Cases!$L$2:$L$368,"Failed") -> 1 | H7: =COUNTIFS(Test_Cases!$C$2:$C$368,A7,Test_Cases!$L$2:$L$368,"Blocked") -> 0 | I7: =COUNTIFS(Test_Cases!$C$2:$C$368,A7,Test_Cases!$L$2:$L$368,"Not_Executed") -> 0 | J7: =IF(E7=0,"Not Covered",IF(G7>0,"Failing",IF(F7=E7,"Fully Covered","Partial"))) -> Failing | K7: =COUNTIF(Bug_Report!$J$2:$J$55,"*"&A7&"*") -> 1
A8: FR-AUTH-07 | B8: Auth | C8: P1 | D8: =_xlfn.TEXTJOIN(", ",TRUE,IF(Test_Cases!$C$2:$C$368=A8,Test_Cases!$A$2:$A$368,"")) | E8: =COUNTIF(Test_Cases!$C$2:$C$368,A8) -> 0 | F8: =COUNTIFS(Test_Cases!$C$2:$C$368,A8,Test_Cases!$L$2:$L$368,"Passed") -> 0 | G8: =COUNTIFS(Test_Cases!$C$2:$C$368,A8,Test_Cases!$L$2:$L$368,"Failed") -> 0 | H8: =COUNTIFS(Test_Cases!$C$2:$C$368,A8,Test_Cases!$L$2:$L$368,"Blocked") -> 0 | I8: =COUNTIFS(Test_Cases!$C$2:$C$368,A8,Test_Cases!$L$2:$L$368,"Not_Executed") -> 0 | J8: =IF(E8=0,"Not Covered",IF(G8>0,"Failing",IF(F8=E8,"Fully Covered","Partial"))) -> Not Covered | K8: =COUNTIF(Bug_Report!$J$2:$J$55,"*"&A8&"*") -> 0
A9: FR-AUTH-08 | B9: Auth | C9: P1 | D9: =_xlfn.TEXTJOIN(", ",TRUE,IF(Test_Cases!$C$2:$C$368=A9,Test_Cases!$A$2:$A$368,"")) | E9: =COUNTIF(Test_Cases!$C$2:$C$368,A9) -> 2 | F9: =COUNTIFS(Test_Cases!$C$2:$C$368,A9,Test_Cases!$L$2:$L$368,"Passed") -> 1 | G9: =COUNTIFS(Test_Cases!$C$2:$C$368,A9,Test_Cases!$L$2:$L$368,"Failed") -> 0 | H9: =COUNTIFS(Test_Cases!$C$2:$C$368,A9,Test_Cases!$L$2:$L$368,"Blocked") -> 0 | I9: =COUNTIFS(Test_Cases!$C$2:$C$368,A9,Test_Cases!$L$2:$L$368,"Not_Executed") -> 1 | J9: =IF(E9=0,"Not Covered",IF(G9>0,"Failing",IF(F9=E9,"Fully Covered","Partial"))) -> Partial | K9: =COUNTIF(Bug_Report!$J$2:$J$55,"*"&A9&"*") -> 0
A10: FR-AUTH-09 | B10: Auth | C10: P1 | D10: =_xlfn.TEXTJOIN(", ",TRUE,IF(Test_Cases!$C$2:$C$368=A10,Test_Cases!$A$2:$A$368,"")) | E10: =COUNTIF(Test_Cases!$C$2:$C$368,A10) -> 0 | F10: =COUNTIFS(Test_Cases!$C$2:$C$368,A10,Test_Cases!$L$2:$L$368,"Passed") -> 0 | G10: =COUNTIFS(Test_Cases!$C$2:$C$368,A10,Test_Cases!$L$2:$L$368,"Failed") -> 0 | H10: =COUNTIFS(Test_Cases!$C$2:$C$368,A10,Test_Cases!$L$2:$L$368,"Blocked") -> 0 | I10: =COUNTIFS(Test_Cases!$C$2:$C$368,A10,Test_Cases!$L$2:$L$368,"Not_Executed") -> 0 | J10: =IF(E10=0,"Not Covered",IF(G10>0,"Failing",IF(F10=E10,"Fully Covered","Partial"))) -> Not Covered | K10: =COUNTIF(Bug_Report!$J$2:$J$55,"*"&A10&"*") -> 0
A11: FR-AUTH-10 | B11: Auth | C11: P1 | D11: =_xlfn.TEXTJOIN(", ",TRUE,IF(Test_Cases!$C$2:$C$368=A11,Test_Cases!$A$2:$A$368,"")) | E11: =COUNTIF(Test_Cases!$C$2:$C$368,A11) -> 1 | F11: =COUNTIFS(Test_Cases!$C$2:$C$368,A11,Test_Cases!$L$2:$L$368,"Passed") -> 1 | G11: =COUNTIFS(Test_Cases!$C$2:$C$368,A11,Test_Cases!$L$2:$L$368,"Failed") -> 0 | H11: =COUNTIFS(Test_Cases!$C$2:$C$368,A11,Test_Cases!$L$2:$L$368,"Blocked") -> 0 | I11: =COUNTIFS(Test_Cases!$C$2:$C$368,A11,Test_Cases!$L$2:$L$368,"Not_Executed") -> 0 | J11: =IF(E11=0,"Not Covered",IF(G11>0,"Failing",IF(F11=E11,"Fully Covered","Partial"))) -> Fully Covered | K11: =COUNTIF(Bug_Report!$J$2:$J$55,"*"&A11&"*") -> 0
A12: FR-AUTH-11 | B12: Tenant Setup | C12: P1 | D12: =_xlfn.TEXTJOIN(", ",TRUE,IF(Test_Cases!$C$2:$C$368=A12,Test_Cases!$A$2:$A$368,"")) | E12: =COUNTIF(Test_Cases!$C$2:$C$368,A12) -> 0 | F12: =COUNTIFS(Test_Cases!$C$2:$C$368,A12,Test_Cases!$L$2:$L$368,"Passed") -> 0 | G12: =COUNTIFS(Test_Cases!$C$2:$C$368,A12,Test_Cases!$L$2:$L$368,"Failed") -> 0 | H12: =COUNTIFS(Test_Cases!$C$2:$C$368,A12,Test_Cases!$L$2:$L$368,"Blocked") -> 0 | I12: =COUNTIFS(Test_Cases!$C$2:$C$368,A12,Test_Cases!$L$2:$L$368,"Not_Executed") -> 0 | J12: =IF(E12=0,"Not Covered",IF(G12>0,"Failing",IF(F12=E12,"Fully Covered","Partial"))) -> Not Covered | K12: =COUNTIF(Bug_Report!$J$2:$J$55,"*"&A12&"*") -> 0
A13: FR-ITA-01 | B13: Tenant Onboarding | C13: P1 | D13: =_xlfn.TEXTJOIN(", ",TRUE,IF(Test_Cases!$C$2:$C$368=A13,Test_Cases!$A$2:$A$368,"")) | E13: =COUNTIF(Test_Cases!$C$2:$C$368,A13) -> 0 | F13: =COUNTIFS(Test_Cases!$C$2:$C$368,A13,Test_Cases!$L$2:$L$368,"Passed") -> 0 | G13: =COUNTIFS(Test_Cases!$C$2:$C$368,A13,Test_Cases!$L$2:$L$368,"Failed") -> 0 | H13: =COUNTIFS(Test_Cases!$C$2:$C$368,A13,Test_Cases!$L$2:$L$368,"Blocked") -> 0 | I13: =COUNTIFS(Test_Cases!$C$2:$C$368,A13,Test_Cases!$L$2:$L$368,"Not_Executed") -> 0 | J13: =IF(E13=0,"Not Covered",IF(G13>0,"Failing",IF(F13=E13,"Fully Covered","Partial"))) -> Not Covered | K13: =COUNTIF(Bug_Report!$J$2:$J$55,"*"&A13&"*") -> 0
... A145: FR-MNT-03 | B145: Compliance | C145: P2 | D145: =_xlfn.TEXTJOIN(", ",TRUE,IF(Test_Cases!$C$2:$C$368=A145,Test_Cases!$A$2:$A$368,"")) | E145: =COUNTIF(Test_Cases!$C$2:$C$368,A145) -> 0 | F145: =COUNTIFS(Test_Cases!$C$2:$C$368,A145,Test_Cases!$L$2:$L$368,"Passed") -> 0 | G145: =COUNTIFS(Test_Cases!$C$2:$C$368,A145,Test_Cases!$L$2:$L$368,"Failed") -> 0 | H145: =COUNTIFS(Test_Cases!$C$2:$C$368,A145,Test_Cases!$L$2:$L$368,"Blocked") -> 0 | I145: =COUNTIFS(Test_Cases!$C$2:$C$368,A145,Test_Cases!$L$2:$L$368,"Not_Executed") -> 0 | J145: =IF(E145=0,"Not Covered",IF(G145>0,"Failing",IF(F145=E145,"Fully Covered","Partial"))) -> Not Covered | K145: =COUNTIF(Bug_Report!$J$2:$J$55,"*"&A145&"*") -> 0
